[
    {
        "id_review": "ChZDSUhNMG9nS0VJQ0FnSUR5alkyVUl3EAE",
        "caption": "The best breakfast sandwiches and everyone is always so pleasant. I literally dream about the golden one.",
        "relative_date": "2 weeks ago",
        "retrieval_date": "2021-04-03",
        "rating": 5.0,
        "username": "Tara Trullinger",
        "n_review_user": 7,
        "n_photo_user": 0,
        "url_user": "https://www.google.com/maps/contrib/100007848523284095525/reviews?hl=en-US",
        "census_block_group": 360470191003
    },
    {
        "id_review": "ChZDSUhNMG9nS0VJQ0FnSUR5c2FLOEV3EAE",
        "caption": "Staff was underwhelming but coffee was good.",
        "relative_date": "3 weeks ago",
        "retrieval_date": "2021-04-03",
        "rating": 4.0,
        "username": "Sweta Sukhadia",
        "n_review_user": 0,
        "n_photo_user": 0,
        "url_user": "https://www.google.com/maps/contrib/102843837054721293192/reviews?hl=en-US",
        "census_block_group": 360470191003
    },
    {
        "id_review": "ChZDSUhNMG9nS0VJQ0FnSUN5cF9mdmNBEAE",
        "caption": "Great coffee and some really delicious prepared foods - the matzo ball soup is soooo good!",
        "relative_date": "a month ago",
        "retrieval_date": "2021-04-03",
        "rating": 5.0,
        "username": "N Busch",
        "n_review_user": 0,
        "n_photo_user": 0,
        "url_user": "https://www.google.com/maps/contrib/105893569533686032152/reviews?hl=en-US",
        "census_block_group": 360470191003
    },
    {
        "id_review": "ChZDSUhNMG9nS0VJQ0FnSUN5LTRMUkJ3EAE",
        "caption": "Delicious coffee, food, and friendly folks",
        "relative_date": "a month ago",
        "retrieval_date": "2021-04-03",
        "rating": 5.0,
        "username": "Nur Asri",
        "n_review_user": 0,
        "n_photo_user": 0,
        "url_user": "https://www.google.com/maps/contrib/105164435791585023696/reviews?hl=en-US",
        "census_block_group": 360470191003
    },
    {
        "id_review": "ChdDSUhNMG9nS0VJQ0FnSUN5X3NYQzJnRRAB",
        "caption": "",
        "relative_date": "2 months ago",
        "retrieval_date": "2021-04-03",
        "rating": 5.0,
        "username": "Silvia Lee",
        "n_review_user": 8,
        "n_photo_user": 0,
        "url_user": "https://www.google.com/maps/contrib/112578857275796334252/reviews?hl=en-US",
        "census_block_group": 360470191003
    },
    {
        "id_review": "ChZDSUhNMG9nS0VJQ0FnSUNTNG8zSmFBEAE",
        "caption": "Nice backyard, great coffee but no flavors if you're looking for that. Really overpriced breakfast sandwiches that are tasty. Always great service!",
        "relative_date": "3 months ago",
        "retrieval_date": "2021-04-03",
        "rating": 4.0,
        "username": "Kaliya Alfred",
        "n_review_user": 0,
        "n_photo_user": 0,
        "url_user": "https://www.google.com/maps/contrib/100587794044822099601/reviews?hl=en-US",
        "census_block_group": 360470191003
    },
    {
        "id_review": "ChZDSUhNMG9nS0VJQ0FnSURpNllYTEN3EAE",
        "caption": "My favorite spot in the neighborhood! I crave these breakfast sandwiches, coffee is always great, and the staff is wonderful.",
        "relative_date": "3 months ago",
        "retrieval_date": "2021-04-03",
        "rating": 5.0,
        "username": "Jordan Thomas",
        "n_review_user": 13,
        "n_photo_user": 0,
        "url_user": "https://www.google.com/maps/contrib/103640062766315391369/reviews?hl=en-US",
        "census_block_group": 360470191003
    },
    {
        "id_review": "ChdDSUhNMG9nS0VJQ0FnSURpZ3YzY3l3RRAB",
        "caption": "Super friendly staff, awesome sandwiches, great coffee.",
        "relative_date": "4 months ago",
        "retrieval_date": "2021-04-03",
        "rating": 5.0,
        "username": "Laurel Delany",
        "n_review_user": 19,
        "n_photo_user": 0,
        "url_user": "https://www.google.com/maps/contrib/112165742540870581325/reviews?hl=en-US",
        "census_block_group": 360470191003
    },
    {
        "id_review": "ChdDSUhNMG9nS0VJQ0FnSURpM0lPRjBRRRAB",
        "caption": "",
        "relative_date": "4 months ago",
        "retrieval_date": "2021-04-03",
        "rating": 5.0,
        "username": "Alix Schreiner",
        "n_review_user": 2,
        "n_photo_user": 0,
        "url_user": "https://www.google.com/maps/contrib/104877889625193100449/reviews?hl=en-US",
        "census_block_group": 360470191003
    },
    {
        "id_review": "ChdDSUhNMG9nS0VJQ0FnSURpOU83VDZRRRAB",
        "caption": "**Ordered takeout during COVID pandemic  Food *The Golden One (Two Fried Eggs, Green Chile, Deer Creek Cheddar & Fried Potato Latke on Portuguese Bun) - Good *Halva Brownie - Good",
        "relative_date": "4 months ago",
        "retrieval_date": "2021-04-03",
        "rating": 4.0,
        "username": "Daniel Pino",
        "n_review_user": 697,
        "n_photo_user": 0,
        "url_user": "https://www.google.com/maps/contrib/115473127409528133759/reviews?hl=en-US",
        "census_block_group": 360470191003
    },
    {
        "id_review": "ChdDSUhNMG9nS0VJQ0FnSURpaUpEd21RRRAB",
        "caption": "",
        "relative_date": "4 months ago",
        "retrieval_date": "2021-04-03",
        "rating": 5.0,
        "username": "Jennifer Jaffe",
        "n_review_user": 25,
        "n_photo_user": 0,
        "url_user": "https://www.google.com/maps/contrib/111635310924339595916/reviews?hl=en-US",
        "census_block_group": 360470191003
    },
    {
        "id_review": "ChdDSUhNMG9nS0VJQ0FnSUNpaGMzYzhnRRAB",
        "caption": "",
        "relative_date": "4 months ago",
        "retrieval_date": "2021-04-03",
        "rating": 4.0,
        "username": "shadiqua mcmillan",
        "n_review_user": 0,
        "n_photo_user": 0,
        "url_user": "https://www.google.com/maps/contrib/109723081186366109177/reviews?hl=en-US",
        "census_block_group": 360470191003
    },
    {
        "id_review": "ChdDSUhNMG9nS0VJQ0FnSUNpNXREX3JBRRAB",
        "caption": "Terrible service, online ordering is recommended yet it tells you a pick up time and then you have to wait another 20 minutes after that.",
        "relative_date": "5 months ago",
        "retrieval_date": "2021-04-03",
        "rating": 1.0,
        "username": "Steph Smith",
        "n_review_user": 11,
        "n_photo_user": 0,
        "url_user": "https://www.google.com/maps/contrib/113242904056764508404/reviews?hl=en-US",
        "census_block_group": 360470191003
    },
    {
        "id_review": "ChZDSUhNMG9nS0VJQ0FnSUNpc3VmMk9nEAE",
        "caption": "Decent overpriced food. Did not get to try the soup because for some reason they serve cold soup in a non-microwaveable container. The whole thing just melted in the microwave when tried to warm up. Thanks!",
        "relative_date": "5 months ago",
        "retrieval_date": "2021-04-03",
        "rating": 3.0,
        "username": "Sebastian Centurion",
        "n_review_user": 1,
        "n_photo_user": 0,
        "url_user": "https://www.google.com/maps/contrib/114281907618197026269/reviews?hl=en-US",
        "census_block_group": 360470191003
    },
    {
        "id_review": "ChdDSUhNMG9nS0VJQ0FnSURDNDltOXV3RRAB",
        "caption": "",
        "relative_date": "5 months ago",
        "retrieval_date": "2021-04-03",
        "rating": 5.0,
        "username": "Kieran Reichert",
        "n_review_user": 2,
        "n_photo_user": 0,
        "url_user": "https://www.google.com/maps/contrib/109199483900565977958/reviews?hl=en-US",
        "census_block_group": 360470191003
    },
    {
        "id_review": "ChdDSUhNMG9nS0VJQ0FnSURDNnY2YTN3RRAB",
        "caption": "",
        "relative_date": "6 months ago",
        "retrieval_date": "2021-04-03",
        "rating": 5.0,
        "username": "Rachel H Park Goto",
        "n_review_user": 0,
        "n_photo_user": 0,
        "url_user": "https://www.google.com/maps/contrib/107010218081861108594/reviews?hl=en-US",
        "census_block_group": 360470191003
    },
    {
        "id_review": "ChZDSUhNMG9nS0VJQ0FnSURDOU9IdEN3EAE",
        "caption": "Delicious coconut macron \ud83d\ude0b",
        "relative_date": "6 months ago",
        "retrieval_date": "2021-04-03",
        "rating": 4.0,
        "username": "shantih cook",
        "n_review_user": 1,
        "n_photo_user": 0,
        "url_user": "https://www.google.com/maps/contrib/104060851614416525688/reviews?hl=en-US",
        "census_block_group": 360470191003
    },
    {
        "id_review": "ChdDSUhNMG9nS0VJQ0FnSURDaUpLdS13RRAB",
        "caption": "Fire breakfast sandwiches. Not cheap but...",
        "relative_date": "6 months ago",
        "retrieval_date": "2021-04-03",
        "rating": 5.0,
        "username": "Jonathan Levin",
        "n_review_user": 0,
        "n_photo_user": 0,
        "url_user": "https://www.google.com/maps/contrib/104686570244652033477/reviews?hl=en-US",
        "census_block_group": 360470191003
    },
    {
        "id_review": "ChdDSUhNMG9nS0VJQ0FnSUNDcjV5dzNBRRAB",
        "caption": "Mediocre customer service at best. This was my first time at Peck\u2019s although I\u2019ve been living in the neighborhood for 5 years. What a mistake. Not only was the staff (multiple people) rude to me, but also to my friend who I was with. I understand Covid has been a difficult time for small businesses, but hospitality was seriously lacking. Only giving 2 stars because the scone was good.",
        "relative_date": "6 months ago",
        "retrieval_date": "2021-04-03",
        "rating": 2.0,
        "username": "Sara Peyser",
        "n_review_user": 11,
        "n_photo_user": 0,
        "url_user": "https://www.google.com/maps/contrib/100392493594869849220/reviews?hl=en-US",
        "census_block_group": 360470191003
    },
    {
        "id_review": "ChZDSUhNMG9nS0VJQ0FnSURNXy02Nld3EAE",
        "caption": "Their shakshuka breakfast sandwich is my go-to order. Although it\u2019s expensive at $11. Glad this place is open again! Little dining garden out back.",
        "relative_date": "6 months ago",
        "retrieval_date": "2021-04-03",
        "rating": 4.0,
        "username": "Natalie Torres",
        "n_review_user": 0,
        "n_photo_user": 0,
        "url_user": "https://www.google.com/maps/contrib/109606501939415192300/reviews?hl=en-US",
        "census_block_group": 360470191003
    },
    {
        "id_review": "ChZDSUhNMG9nS0VJQ0FnSUNDNWRERGV3EAE",
        "caption": "",
        "relative_date": "7 months ago",
        "retrieval_date": "2021-04-03",
        "rating": 5.0,
        "username": "Brant Wall",
        "n_review_user": 12,
        "n_photo_user": 0,
        "url_user": "https://www.google.com/maps/contrib/112441023599852255031/reviews?hl=en-US",
        "census_block_group": 360470191003
    },
    {
        "id_review": "ChZDSUhNMG9nS0VJQ0FnSUM4eXZURklREAE",
        "caption": "Amazing cold brew and pastries + the breakfast sandwiches are great too. Most importantly, all the baristas and employees are always friendly and provide great service!",
        "relative_date": "9 months ago",
        "retrieval_date": "2021-04-03",
        "rating": 5.0,
        "username": "Amanda Liu",
        "n_review_user": 27,
        "n_photo_user": 0,
        "url_user": "https://www.google.com/maps/contrib/103095781571665562022/reviews?hl=en-US",
        "census_block_group": 360470191003
    },
    {
        "id_review": "ChZDSUhNMG9nS0VJQ0FnSUM4MEoyaGRREAE",
        "caption": "",
        "relative_date": "9 months ago",
        "retrieval_date": "2021-04-03",
        "rating": 5.0,
        "username": "Coleman Craddock-Willis",
        "n_review_user": 0,
        "n_photo_user": 0,
        "url_user": "https://www.google.com/maps/contrib/107407680693257673780/reviews?hl=en-US",
        "census_block_group": 360470191003
    },
    {
        "id_review": "ChZDSUhNMG9nS0VJQ0FnSURjaW95d1F3EAE",
        "caption": "",
        "relative_date": "9 months ago",
        "retrieval_date": "2021-04-03",
        "rating": 5.0,
        "username": "Stephane Tu",
        "n_review_user": 0,
        "n_photo_user": 0,
        "url_user": "https://www.google.com/maps/contrib/100438228419962894304/reviews?hl=en-US",
        "census_block_group": 360470191003
    },
    {
        "id_review": "ChdDSUhNMG9nS0VJQ0FnSURjdklYeS1BRRAB",
        "caption": "Coffee (flatwhite) was tasteless and lox sandwich greasy and average. Service inefficient and waitress insolent (busy flirting with the barista and obviously not caring about the line of customers. became snappy when asked to actually serve the coffee ordered online 30 mins ago)",
        "relative_date": "10 months ago",
        "retrieval_date": "2021-04-03",
        "rating": 2.0,
        "username": "Margot Desachy",
        "n_review_user": 0,
        "n_photo_user": 0,
        "url_user": "https://www.google.com/maps/contrib/118198244667339097633/reviews?hl=en-US",
        "census_block_group": 360470191003
    },
    {
        "id_review": "ChdDSUhNMG9nS0VJQ0FnSURjM04yRjlnRRAB",
        "caption": "Lived near Peck\u2019s for 3 years and it has been my go-to for great coffee and food. Quaint backyard is perfect for remote work or meeting up with friends and their wide variety of sandwiches and baked goods never disappoint.",
        "relative_date": "10 months ago",
        "retrieval_date": "2021-04-03",
        "rating": 5.0,
        "username": "John Farley",
        "n_review_user": 5,
        "n_photo_user": 0,
        "url_user": "https://www.google.com/maps/contrib/103169365042619782241/reviews?hl=en-US",
        "census_block_group": 360470191003
    },
    {
        "id_review": "ChdDSUhNMG9nS0VJQ0FnSURjNUlmVm9RRRAB",
        "caption": "",
        "relative_date": "10 months ago",
        "retrieval_date": "2021-04-03",
        "rating": 5.0,
        "username": "Sean Diaz",
        "n_review_user": 2,
        "n_photo_user": 0,
        "url_user": "https://www.google.com/maps/contrib/101986924226310550662/reviews?hl=en-US",
        "census_block_group": 360470191003
    },
    {
        "id_review": "ChZDSUhNMG9nS0VJQ0FnSURjaE15dGZnEAE",
        "caption": "every time i come here the baristas are so kind & welcoming! love the coffee and the food, a neighborhood staple \ud83d\ude0b",
        "relative_date": "10 months ago",
        "retrieval_date": "2021-04-03",
        "rating": 5.0,
        "username": "Shira Kindler",
        "n_review_user": 1,
        "n_photo_user": 0,
        "url_user": "https://www.google.com/maps/contrib/106885395562104945726/reviews?hl=en-US",
        "census_block_group": 360470191003
    },
    {
        "id_review": "ChdDSUhNMG9nS0VJQ0FnSURzcm9mVHhBRRAB",
        "caption": "Old fashioned scrumptious baked goods and delicacies! It's the trendy neighborhood place to go!",
        "relative_date": "a year ago",
        "retrieval_date": "2021-04-03",
        "rating": 5.0,
        "username": "Michele Lee",
        "n_review_user": 31,
        "n_photo_user": 0,
        "url_user": "https://www.google.com/maps/contrib/118263071072903662318/reviews?hl=en-US",
        "census_block_group": 360470191003
    },
    {
        "id_review": "ChZDSUhNMG9nS0VJQ0FnSUNzeTliOU9REAE",
        "caption": "Arguably the best breakfast sandwich in Brooklyn. They allow you to call ahead and order and the staff is always extremely polite. I always leave this place in a better mood than I arrived in.",
        "relative_date": "a year ago",
        "retrieval_date": "2021-04-03",
        "rating": 5.0,
        "username": "Alisha Hallmark",
        "n_review_user": 0,
        "n_photo_user": 0,
        "url_user": "https://www.google.com/maps/contrib/101723804248834567814/reviews?hl=en-US",
        "census_block_group": 360470191003
    },
    {
        "id_review": "ChdDSUhNMG9nS0VJQ0FnSUNzX2RLeHBRRRAB",
        "caption": "Excellent service Great baked goods. Decent Coffee.",
        "relative_date": "a year ago",
        "retrieval_date": "2021-04-03",
        "rating": 5.0,
        "username": "maritza dilbert",
        "n_review_user": 5,
        "n_photo_user": 0,
        "url_user": "https://www.google.com/maps/contrib/114786053898557057437/reviews?hl=en-US",
        "census_block_group": 360470191003
    },
    {
        "id_review": "ChdDSUhNMG9nS0VJQ0FnSUNzamRTSHdRRRAB",
        "caption": "",
        "relative_date": "a year ago",
        "retrieval_date": "2021-04-03",
        "rating": 5.0,
        "username": "Paul Hoffman",
        "n_review_user": 4,
        "n_photo_user": 0,
        "url_user": "https://www.google.com/maps/contrib/102258611420833445995/reviews?hl=en-US",
        "census_block_group": 360470191003
    },
    {
        "id_review": "ChZDSUhNMG9nS0VJQ0FnSUNzbnBmMU5nEAE",
        "caption": "",
        "relative_date": "a year ago",
        "retrieval_date": "2021-04-03",
        "rating": 4.0,
        "username": "oscar simo de leon",
        "n_review_user": 0,
        "n_photo_user": 0,
        "url_user": "https://www.google.com/maps/contrib/105483009528630631368/reviews?hl=en-US",
        "census_block_group": 360470191003
    },
    {
        "id_review": "ChdDSUhNMG9nS0VJQ0FnSUNzNnNLQ3VRRRAB",
        "caption": "",
        "relative_date": "a year ago",
        "retrieval_date": "2021-04-03",
        "rating": 2.0,
        "username": "S. Melgos",
        "n_review_user": 0,
        "n_photo_user": 0,
        "url_user": "https://www.google.com/maps/contrib/103947487982990190772/reviews?hl=en-US",
        "census_block_group": 360470191003
    },
    {
        "id_review": "ChZDSUhNMG9nS0VJQ0FnSUNzM08zOGFBEAE",
        "caption": "",
        "relative_date": "a year ago",
        "retrieval_date": "2021-04-03",
        "rating": 5.0,
        "username": "Bibi Balkarran",
        "n_review_user": 0,
        "n_photo_user": 0,
        "url_user": "https://www.google.com/maps/contrib/100418963280286749726/reviews?hl=en-US",
        "census_block_group": 360470191003
    },
    {
        "id_review": "ChdDSUhNMG9nS0VJQ0FnSUNzblAzdHpRRRAB",
        "caption": "Good run-to coffee shop. They have lunch also!",
        "relative_date": "a year ago",
        "retrieval_date": "2021-04-03",
        "rating": 5.0,
        "username": "Akif Zaman",
        "n_review_user": 0,
        "n_photo_user": 0,
        "url_user": "https://www.google.com/maps/contrib/110252138723816594669/reviews?hl=en-US",
        "census_block_group": 360470191003
    },
    {
        "id_review": "ChZDSUhNMG9nS0VJQ0FnSUNzcEp2QWZREAE",
        "caption": "Great coffee and luncheonette spot.",
        "relative_date": "a year ago",
        "retrieval_date": "2021-04-03",
        "rating": 4.0,
        "username": "Nathan Meshberg",
        "n_review_user": 0,
        "n_photo_user": 0,
        "url_user": "https://www.google.com/maps/contrib/108308307474060528318/reviews?hl=en-US",
        "census_block_group": 360470191003
    },
    {
        "id_review": "ChZDSUhNMG9nS0VJQ0FnSURNajdpTVpnEAE",
        "caption": "This place has the best chocolate chip cookie in Brooklyn.  I have tried almost every bakery in the greater north brooklyn area (park slope to Bushwick) and this place is tippy top. The breakfast sandwich experience is pleasant but the cookie is not to be missed",
        "relative_date": "a year ago",
        "retrieval_date": "2021-04-03",
        "rating": 5.0,
        "username": "Benjamin Cohen",
        "n_review_user": 3,
        "n_photo_user": 0,
        "url_user": "https://www.google.com/maps/contrib/101371710803269513454/reviews?hl=en-US",
        "census_block_group": 360470191003
    },
    {
        "id_review": "ChdDSUhNMG9nS0VJQ0FnSURNM2VMUnRRRRAB",
        "caption": "",
        "relative_date": "a year ago",
        "retrieval_date": "2021-04-03",
        "rating": 5.0,
        "username": "Mark Trumpbour",
        "n_review_user": 0,
        "n_photo_user": 0,
        "url_user": "https://www.google.com/maps/contrib/104349398906807523399/reviews?hl=en-US",
        "census_block_group": 360470191003
    },
    {
        "id_review": "ChZDSUhNMG9nS0VJQ0FnSURNaVpfclBBEAE",
        "caption": "WOW. Hands down best coffee shop food I\u2019ve ever had.",
        "relative_date": "a year ago",
        "retrieval_date": "2021-04-03",
        "rating": 5.0,
        "username": "Cynthia Gonzalez",
        "n_review_user": 4,
        "n_photo_user": 0,
        "url_user": "https://www.google.com/maps/contrib/114934615220204292869/reviews?hl=en-US",
        "census_block_group": 360470191003
    },
    {
        "id_review": "ChdDSUhNMG9nS0VJQ0FnSURNX29xTXJBRRAB",
        "caption": "",
        "relative_date": "a year ago",
        "retrieval_date": "2021-04-03",
        "rating": 5.0,
        "username": "Avi Tapuchi",
        "n_review_user": 0,
        "n_photo_user": 0,
        "url_user": "https://www.google.com/maps/contrib/107766429657149121870/reviews?hl=en-US",
        "census_block_group": 360470191003
    },
    {
        "id_review": "ChdDSUhNMG9nS0VJQ0FnSURNMU1lZjdnRRAB",
        "caption": "",
        "relative_date": "a year ago",
        "retrieval_date": "2021-04-03",
        "rating": 5.0,
        "username": "Brian McKain",
        "n_review_user": 0,
        "n_photo_user": 0,
        "url_user": "https://www.google.com/maps/contrib/113921054983753018764/reviews?hl=en-US",
        "census_block_group": 360470191003
    },
    {
        "id_review": "ChdDSUhNMG9nS0VJQ0FnSUNNNWEzRzl3RRAB",
        "caption": "Great breakfast sandwich with Portuguese bread! The cappuccino was excellent too!",
        "relative_date": "a year ago",
        "retrieval_date": "2021-04-03",
        "rating": 5.0,
        "username": "Rosana Cordova",
        "n_review_user": 0,
        "n_photo_user": 0,
        "url_user": "https://www.google.com/maps/contrib/112918104273732062447/reviews?hl=en-US",
        "census_block_group": 360470191003
    },
    {
        "id_review": "ChZDSUhNMG9nS0VJQ0FnSUQwcmZLYVhnEAE",
        "caption": "Most delectable \ud83d\ude0b a real local favorite \ud83d\udc4d",
        "relative_date": "a year ago",
        "retrieval_date": "2021-04-03",
        "rating": 5.0,
        "username": "John Hardy",
        "n_review_user": 0,
        "n_photo_user": 0,
        "url_user": "https://www.google.com/maps/contrib/108646055626101346737/reviews?hl=en-US",
        "census_block_group": 360470191003
    },
    {
        "id_review": "ChdDSUhNMG9nS0VJQ0FnSUQwM29MaXFRRRAB",
        "caption": "One of the nest egg sandwiches of my life!!",
        "relative_date": "a year ago",
        "retrieval_date": "2021-04-03",
        "rating": 5.0,
        "username": "John Davison",
        "n_review_user": 0,
        "n_photo_user": 0,
        "url_user": "https://www.google.com/maps/contrib/117694321653106179997/reviews?hl=en-US",
        "census_block_group": 360470191003
    },
    {
        "id_review": "ChZDSUhNMG9nS0VJQ0FnSUQwalBDZ1JBEAE",
        "caption": "(Translated by Google) One of the best bakery in the area, the coffee is very good, also growing ($ 3.5 anyway), excellent pastries and crispy baguette. The welcome is cordial without more. The place is a bit small to consume on the spot  (Original) Une des meilleures boulangerie du coin,  le caf\u00e9 y est tres bon,  croissants aussi (3,5 $ quand meme),  les patisseries excellentes et la baguette croustillantes.  L'accueil est cordial sans plus.  L'endroit est un peu petit pour consommer sur place",
        "relative_date": "a year ago",
        "retrieval_date": "2021-04-03",
        "rating": 4.0,
        "username": "G Salles",
        "n_review_user": 35,
        "n_photo_user": 0,
        "url_user": "https://www.google.com/maps/contrib/116750943177085490711/reviews?hl=en-US",
        "census_block_group": 360470191003
    },
    {
        "id_review": "ChdDSUhNMG9nS0VJQ0FnSUMwbjVMZXNnRRAB",
        "caption": "Phenomenal breakfast sandwiches!",
        "relative_date": "a year ago",
        "retrieval_date": "2021-04-03",
        "rating": 5.0,
        "username": "Garrett Williams",
        "n_review_user": 0,
        "n_photo_user": 0,
        "url_user": "https://www.google.com/maps/contrib/107346411425413310505/reviews?hl=en-US",
        "census_block_group": 360470191003
    },
    {
        "id_review": "ChZDSUhNMG9nS0VJQ0FnSURra2V5bFp3EAE",
        "caption": "",
        "relative_date": "a year ago",
        "retrieval_date": "2021-04-03",
        "rating": 5.0,
        "username": "Mazal Bienstock",
        "n_review_user": 2,
        "n_photo_user": 0,
        "url_user": "https://www.google.com/maps/contrib/108104606875240394117/reviews?hl=en-US",
        "census_block_group": 360470191003
    },
    {
        "id_review": "ChZDSUhNMG9nS0VJQ0FnSUMwcHBpbGN3EAE",
        "caption": "One of my favorites spot to take breakfast... Their hot cocoa is really good... The place and the staff are nice... Thank you",
        "relative_date": "a year ago",
        "retrieval_date": "2021-04-03",
        "rating": 5.0,
        "username": "Carmen L\u00f3pez",
        "n_review_user": 0,
        "n_photo_user": 0,
        "url_user": "https://www.google.com/maps/contrib/114418048619561718588/reviews?hl=en-US",
        "census_block_group": 360470191003
    },
    {
        "id_review": "ChZDSUhNMG9nS0VJQ0FnSURVcV9DaUR3EAE",
        "caption": "",
        "relative_date": "a year ago",
        "retrieval_date": "2021-04-03",
        "rating": 1.0,
        "username": "Leah Farrell",
        "n_review_user": 0,
        "n_photo_user": 0,
        "url_user": "https://www.google.com/maps/contrib/108838139623459097479/reviews?hl=en-US",
        "census_block_group": 360470191003
    },
    {
        "id_review": "ChdDSUhNMG9nS0VJQ0FnSURVbzcyZmhnRRAB",
        "caption": "",
        "relative_date": "a year ago",
        "retrieval_date": "2021-04-03",
        "rating": 5.0,
        "username": "Saud Almoayyed",
        "n_review_user": 2,
        "n_photo_user": 0,
        "url_user": "https://www.google.com/maps/contrib/115933963340196570903/reviews?hl=en-US",
        "census_block_group": 360470191003
    },
    {
        "id_review": "ChdDSUhNMG9nS0VJQ0FnSURVMWY2aWx3RRAB",
        "caption": "Excellent breakfast sandwich and friendly service!",
        "relative_date": "a year ago",
        "retrieval_date": "2021-04-03",
        "rating": 5.0,
        "username": "Adi Kamdar",
        "n_review_user": 0,
        "n_photo_user": 0,
        "url_user": "https://www.google.com/maps/contrib/116098191870465579122/reviews?hl=en-US",
        "census_block_group": 360470191003
    },
    {
        "id_review": "ChdDSUhNMG9nS0VJQ0FnSURVNWVfSC13RRAB",
        "caption": "If you need a sandwich and a beer and a coffee and something that isn't Thai food on Myrtle Avenue then this would be your jam.",
        "relative_date": "a year ago",
        "retrieval_date": "2021-04-03",
        "rating": 5.0,
        "username": "William Moore",
        "n_review_user": 0,
        "n_photo_user": 0,
        "url_user": "https://www.google.com/maps/contrib/100976429300808355612/reviews?hl=en-US",
        "census_block_group": 360470191003
    },
    {
        "id_review": "ChZDSUhNMG9nS0VJQ0FnSURVdnFfWmZnEAE",
        "caption": "Best breakfast sandwiches & pastries in Brooklyn!  The chocolate almond croissant is off the hook.  And great coffee, backyard, and beer selection - what more could you want!",
        "relative_date": "a year ago",
        "retrieval_date": "2021-04-03",
        "rating": 5.0,
        "username": "Justin Green",
        "n_review_user": 7,
        "n_photo_user": 0,
        "url_user": "https://www.google.com/maps/contrib/109680651528424377616/reviews?hl=en-US",
        "census_block_group": 360470191003
    },
    {
        "id_review": "ChdDSUhNMG9nS0VJQ0FnSURVNUxuYnZRRRAB",
        "caption": "Place charges you 50 cents for ice in an iced drink. As if they don't rob you enough on the price of coffee in general. Stay away from greedy coffee shops like this",
        "relative_date": "a year ago",
        "retrieval_date": "2021-04-03",
        "rating": 1.0,
        "username": "Anthony Pennachio",
        "n_review_user": 25,
        "n_photo_user": 0,
        "url_user": "https://www.google.com/maps/contrib/112374941090495966646/reviews?hl=en-US",
        "census_block_group": 360470191003
    },
    {
        "id_review": "ChZDSUhNMG9nS0VJQ0FnSUNVOVlQeU1REAE",
        "caption": "",
        "relative_date": "a year ago",
        "retrieval_date": "2021-04-03",
        "rating": 4.0,
        "username": "David Kaplan",
        "n_review_user": 0,
        "n_photo_user": 0,
        "url_user": "https://www.google.com/maps/contrib/113255667555755574678/reviews?hl=en-US",
        "census_block_group": 360470191003
    },
    {
        "id_review": "ChdDSUhNMG9nS0VJQ0FnSUNVaWJtbi13RRAB",
        "caption": "Yummy variations on egg sandwiches, & a few other sandwiches. Good pastries. Tea coffee. Usually friendly service. Lovely backyard. Also a nice place to pick up good quality (slightly pricey) prepared food, bread, cheese, ice cream, & beer.",
        "relative_date": "a year ago",
        "retrieval_date": "2021-04-03",
        "rating": 4.0,
        "username": "Sarah W",
        "n_review_user": 0,
        "n_photo_user": 0,
        "url_user": "https://www.google.com/maps/contrib/114636785864621850477/reviews?hl=en-US",
        "census_block_group": 360470191003
    },
    {
        "id_review": "ChdDSUhNMG9nS0VJQ0FnSURrajlfWHl3RRAB",
        "caption": "",
        "relative_date": "a year ago",
        "retrieval_date": "2021-04-03",
        "rating": 4.0,
        "username": "Anastasia Sh",
        "n_review_user": 0,
        "n_photo_user": 0,
        "url_user": "https://www.google.com/maps/contrib/100522453775263941397/reviews?hl=en-US",
        "census_block_group": 360470191003
    },
    {
        "id_review": "ChZDSUhNMG9nS0VJQ0FnSURrLU1iaGJnEAE",
        "caption": "Delicious sandwiches for breakfast! Very friendly staff too. Spotted some great looking cakes and cheese as well.",
        "relative_date": "a year ago",
        "retrieval_date": "2021-04-03",
        "rating": 5.0,
        "username": "Charlotte Evans",
        "n_review_user": 0,
        "n_photo_user": 0,
        "url_user": "https://www.google.com/maps/contrib/117273496467565934571/reviews?hl=en-US",
        "census_block_group": 360470191003
    },
    {
        "id_review": "ChdDSUhNMG9nS0VJQ0FnSUQ0cGJUYTd3RRAB",
        "caption": "",
        "relative_date": "a year ago",
        "retrieval_date": "2021-04-03",
        "rating": 5.0,
        "username": "Brooklyn Black",
        "n_review_user": 14,
        "n_photo_user": 0,
        "url_user": "https://www.google.com/maps/contrib/104659717643973196060/reviews?hl=en-US",
        "census_block_group": 360470191003
    },
    {
        "id_review": "ChZDSUhNMG9nS0VJQ0FnSUQ0NXVfWFF3EAE",
        "caption": "",
        "relative_date": "a year ago",
        "retrieval_date": "2021-04-03",
        "rating": 5.0,
        "username": "Mack Burns",
        "n_review_user": 0,
        "n_photo_user": 0,
        "url_user": "https://www.google.com/maps/contrib/111040941127566320204/reviews?hl=en-US",
        "census_block_group": 360470191003
    },
    {
        "id_review": "ChZDSUhNMG9nS0VJQ0FnSUNZOEo2UmFREAE",
        "caption": "Go here, get anything, enjoy your day. Great little shop.",
        "relative_date": "a year ago",
        "retrieval_date": "2021-04-03",
        "rating": 5.0,
        "username": "Rianna Rose",
        "n_review_user": 0,
        "n_photo_user": 0,
        "url_user": "https://www.google.com/maps/contrib/112529693095916218182/reviews?hl=en-US",
        "census_block_group": 360470191003
    },
    {
        "id_review": "ChdDSUhNMG9nS0VJQ0FnSUM0d0tXcjlnRRAB",
        "caption": "",
        "relative_date": "a year ago",
        "retrieval_date": "2021-04-03",
        "rating": 4.0,
        "username": "Reyes Alvarez",
        "n_review_user": 0,
        "n_photo_user": 0,
        "url_user": "https://www.google.com/maps/contrib/113619767586184493070/reviews?hl=en-US",
        "census_block_group": 360470191003
    },
    {
        "id_review": "ChZDSUhNMG9nS0VJQ0FnSURZazUtRWNBEAE",
        "caption": "Love this place.  Killer coffee and breakfast sandys.",
        "relative_date": "a year ago",
        "retrieval_date": "2021-04-03",
        "rating": 5.0,
        "username": "John Carlucci",
        "n_review_user": 0,
        "n_photo_user": 0,
        "url_user": "https://www.google.com/maps/contrib/110987292452365567412/reviews?hl=en-US",
        "census_block_group": 360470191003
    },
    {
        "id_review": "ChdDSUhNMG9nS0VJQ0FnSURZbXBYOWxnRRAB",
        "caption": "",
        "relative_date": "a year ago",
        "retrieval_date": "2021-04-03",
        "rating": 1.0,
        "username": "Maria German",
        "n_review_user": 0,
        "n_photo_user": 0,
        "url_user": "https://www.google.com/maps/contrib/115776577251086252668/reviews?hl=en-US",
        "census_block_group": 360470191003
    },
    {
        "id_review": "ChZDSUhNMG9nS0VJQ0FnSURZNHRfeFJ3EAE",
        "caption": "Great place for Sunday morning.  Great pastries and sandwiches! A nice neighborhood feel.  Totally fine, you should go!",
        "relative_date": "a year ago",
        "retrieval_date": "2021-04-03",
        "rating": 5.0,
        "username": "Gary Benowitz",
        "n_review_user": 34,
        "n_photo_user": 0,
        "url_user": "https://www.google.com/maps/contrib/111898722049530982189/reviews?hl=en-US",
        "census_block_group": 360470191003
    },
    {
        "id_review": "ChZDSUhNMG9nS0VJQ0FnSUNZZ3B5MVVnEAE",
        "caption": "",
        "relative_date": "a year ago",
        "retrieval_date": "2021-04-03",
        "rating": 2.0,
        "username": "Tim Grucza",
        "n_review_user": 6,
        "n_photo_user": 0,
        "url_user": "https://www.google.com/maps/contrib/100424784537655762574/reviews?hl=en-US",
        "census_block_group": 360470191003
    },
    {
        "id_review": "ChdDSUhNMG9nS0VJQ0FnSURvMTlEWTZRRRAB",
        "caption": "",
        "relative_date": "2 years ago",
        "retrieval_date": "2021-04-03",
        "rating": 3.0,
        "username": "Z Walsh",
        "n_review_user": 1,
        "n_photo_user": 0,
        "url_user": "https://www.google.com/maps/contrib/117663384500689405956/reviews?hl=en-US",
        "census_block_group": 360470191003
    },
    {
        "id_review": "ChZDSUhNMG9nS0VJQ0FnSURvdTltT0NBEAE",
        "caption": "My favourite place on Myrtle for coffee, sandwiches and pastries. The deli is amazing too. \u2764\ufe0f",
        "relative_date": "2 years ago",
        "retrieval_date": "2021-04-03",
        "rating": 5.0,
        "username": "Chris Mayes-Wright",
        "n_review_user": 33,
        "n_photo_user": 0,
        "url_user": "https://www.google.com/maps/contrib/102713506361365862424/reviews?hl=en-US",
        "census_block_group": 360470191003
    },
    {
        "id_review": "ChZDSUhNMG9nS0VJQ0FnSUNvbTVMRUhBEAE",
        "caption": "",
        "relative_date": "2 years ago",
        "retrieval_date": "2021-04-03",
        "rating": 3.0,
        "username": "Sarah Haider",
        "n_review_user": 0,
        "n_photo_user": 0,
        "url_user": "https://www.google.com/maps/contrib/114985200220442967347/reviews?hl=en-US",
        "census_block_group": 360470191003
    },
    {
        "id_review": "ChZDSUhNMG9nS0VJQ0FnSUNvaTVYOWN3EAE",
        "caption": "",
        "relative_date": "2 years ago",
        "retrieval_date": "2021-04-03",
        "rating": 5.0,
        "username": "Sarah Smith",
        "n_review_user": 0,
        "n_photo_user": 0,
        "url_user": "https://www.google.com/maps/contrib/102329805083428073345/reviews?hl=en-US",
        "census_block_group": 360470191003
    },
    {
        "id_review": "ChZDSUhNMG9nS0VJQ0FnSUNvb1lINFZREAE",
        "caption": "",
        "relative_date": "2 years ago",
        "retrieval_date": "2021-04-03",
        "rating": 5.0,
        "username": "Murissova Nana",
        "n_review_user": 0,
        "n_photo_user": 0,
        "url_user": "https://www.google.com/maps/contrib/107061527246657389469/reviews?hl=en-US",
        "census_block_group": 360470191003
    },
    {
        "id_review": "ChZDSUhNMG9nS0VJQ0FnSUNvM3JLc0tBEAE",
        "caption": "Love the coffee",
        "relative_date": "2 years ago",
        "retrieval_date": "2021-04-03",
        "rating": 5.0,
        "username": "Lindsay Einhorn",
        "n_review_user": 0,
        "n_photo_user": 0,
        "url_user": "https://www.google.com/maps/contrib/110138642387180615968/reviews?hl=en-US",
        "census_block_group": 360470191003
    },
    {
        "id_review": "ChdDSUhNMG9nS0VJQ0FnSURnajhxNF9BRRAB",
        "caption": "The coffee is pricey but good. The atmosphere is nice, clean yet cozy. I love the window paintings they always change up. The food here is also pricey but I would say the coconut macaroons and cheese are worth the money. The cookies are too dry in my opinion tho.",
        "relative_date": "2 years ago",
        "retrieval_date": "2021-04-03",
        "rating": 5.0,
        "username": "Josie Thompson",
        "n_review_user": 0,
        "n_photo_user": 0,
        "url_user": "https://www.google.com/maps/contrib/113256866378377199335/reviews?hl=en-US",
        "census_block_group": 360470191003
    },
    {
        "id_review": "ChZDSUhNMG9nS0VJQ0FnSUNvOFBXUldnEAE",
        "caption": "Meh. Very limited food menu.",
        "relative_date": "2 years ago",
        "retrieval_date": "2021-04-03",
        "rating": 2.0,
        "username": "Katina Parker",
        "n_review_user": 0,
        "n_photo_user": 0,
        "url_user": "https://www.google.com/maps/contrib/115683489629675811058/reviews?hl=en-US",
        "census_block_group": 360470191003
    },
    {
        "id_review": "ChdDSUhNMG9nS0VJQ0FnSURJNy1TV19BRRAB",
        "caption": "",
        "relative_date": "2 years ago",
        "retrieval_date": "2021-04-03",
        "rating": 5.0,
        "username": "David Jalbert-Gagnier",
        "n_review_user": 0,
        "n_photo_user": 0,
        "url_user": "https://www.google.com/maps/contrib/107187412706953464003/reviews?hl=en-US",
        "census_block_group": 360470191003
    },
    {
        "id_review": "ChdDSUhNMG9nS0VJQ0FnSURJejZuZjZBRRAB",
        "caption": "",
        "relative_date": "2 years ago",
        "retrieval_date": "2021-04-03",
        "rating": 5.0,
        "username": "Melissa Noble",
        "n_review_user": 8,
        "n_photo_user": 0,
        "url_user": "https://www.google.com/maps/contrib/113522405898544111791/reviews?hl=en-US",
        "census_block_group": 360470191003
    },
    {
        "id_review": "ChZDSUhNMG9nS0VJQ0FnSURJODctVlNBEAE",
        "caption": "Really good coffee, high quality food and thoughtful service.",
        "relative_date": "2 years ago",
        "retrieval_date": "2021-04-03",
        "rating": 5.0,
        "username": "Louis Cato",
        "n_review_user": 0,
        "n_photo_user": 0,
        "url_user": "https://www.google.com/maps/contrib/105991652516422845716/reviews?hl=en-US",
        "census_block_group": 360470191003
    },
    {
        "id_review": "ChZDSUhNMG9nS0VJQ0FnSURJX2RUZE5REAE",
        "caption": "",
        "relative_date": "2 years ago",
        "retrieval_date": "2021-04-03",
        "rating": 4.0,
        "username": "Tryg Siverson",
        "n_review_user": 0,
        "n_photo_user": 0,
        "url_user": "https://www.google.com/maps/contrib/112209627645080369367/reviews?hl=en-US",
        "census_block_group": 360470191003
    },
    {
        "id_review": "ChdDSUhNMG9nS0VJQ0FnSURJcnN6aDBRRRAB",
        "caption": "I love Pecks. They have an arsenal of fresh baked goods each morning from sandwiches to quiches to all the sweets you need. They serve made-to-order sandwiches for breakfast and lunch, including a basic bacon egg and cheese that is actually good because they actually use quality bacon, egg, cheese and bread. Great selection of beer and cider in the cans to go, the prepare a mean coffee (cold brew, espresso, lattemoccachinos... all that \ud83d\ude09) and, get this, they actually have a meat and cheese section and will slice you meats/cheeses like any other fancy meat and cheese shop. Though their selection of meat and cheese is small, it is in fact one of the most well-curated in the city. They will also preorder you whole hunks if you need for a big party. 10/10, spend your money here.",
        "relative_date": "2 years ago",
        "retrieval_date": "2021-04-03",
        "rating": 5.0,
        "username": "Bryan Lindner",
        "n_review_user": 0,
        "n_photo_user": 0,
        "url_user": "https://www.google.com/maps/contrib/113696054632374801301/reviews?hl=en-US",
        "census_block_group": 360470191003
    },
    {
        "id_review": "ChdDSUhNMG9nS0VJQ0FnSURJdkozaHFnRRAB",
        "caption": "Stopped in quickly for a hot chocolate was great!",
        "relative_date": "2 years ago",
        "retrieval_date": "2021-04-03",
        "rating": 5.0,
        "username": "Linda Wolfe",
        "n_review_user": 0,
        "n_photo_user": 0,
        "url_user": "https://www.google.com/maps/contrib/116442035702115839789/reviews?hl=en-US",
        "census_block_group": 360470191003
    },
    {
        "id_review": "ChdDSUhNMG9nS0VJQ0FnSURJMFBmQnh3RRAB",
        "caption": "",
        "relative_date": "2 years ago",
        "retrieval_date": "2021-04-03",
        "rating": 5.0,
        "username": "terson dorlouis",
        "n_review_user": 0,
        "n_photo_user": 0,
        "url_user": "https://www.google.com/maps/contrib/117661461248858352399/reviews?hl=en-US",
        "census_block_group": 360470191003
    },
    {
        "id_review": "ChZDSUhNMG9nS0VJQ0FnSURJNE5HUE1BEAE",
        "caption": "Amazing but overpriced. $19 for a rotisserie chicken. $15 - fine. $19 - come on, that chicken isn\u2019t making me breakfast the next morning.",
        "relative_date": "2 years ago",
        "retrieval_date": "2021-04-03",
        "rating": 5.0,
        "username": "Laurel Baldwin DeCicco",
        "n_review_user": 0,
        "n_photo_user": 0,
        "url_user": "https://www.google.com/maps/contrib/106064938126970695169/reviews?hl=en-US",
        "census_block_group": 360470191003
    },
    {
        "id_review": "ChZDSUhNMG9nS0VJQ0FnSUNJcTdIZWR3EAE",
        "caption": "",
        "relative_date": "2 years ago",
        "retrieval_date": "2021-04-03",
        "rating": 4.0,
        "username": "Katie",
        "n_review_user": 0,
        "n_photo_user": 0,
        "url_user": "https://www.google.com/maps/contrib/104473813128766324924/reviews?hl=en-US",
        "census_block_group": 360470191003
    },
    {
        "id_review": "ChdDSUhNMG9nS0VJQ0FnSUNJa3ZlMG1RRRAB",
        "caption": "Great deli serving breakfast, sandwiches and a range of takeaway items. Highlights would have to be the rotisserie chicken and matzo ball soup. PLEASE PLEASE PLEASE sort out your breakfast / lunch change over - 30/40 minutes with no sandwiches at 12-12:30, really !?!?!",
        "relative_date": "2 years ago",
        "retrieval_date": "2021-04-03",
        "rating": 3.0,
        "username": "James T",
        "n_review_user": 0,
        "n_photo_user": 0,
        "url_user": "https://www.google.com/maps/contrib/107114492389308193817/reviews?hl=en-US",
        "census_block_group": 360470191003
    },
    {
        "id_review": "ChdDSUhNMG9nS0VJQ0FnSUNvLVlmUnpRRRAB",
        "caption": "Cool neighborhood spot for unique sandwiches (both breakfast and lunch), good coffee and craft beers. Go for breakfast and order the New Mexican Sandwich. Not much interior seating, so either check them out in the summer when you can sit in their backyard, or grab it to go.",
        "relative_date": "2 years ago",
        "retrieval_date": "2021-04-03",
        "rating": 5.0,
        "username": "Jonathan Wood",
        "n_review_user": 0,
        "n_photo_user": 0,
        "url_user": "https://www.google.com/maps/contrib/110054948401254301509/reviews?hl=en-US",
        "census_block_group": 360470191003
    },
    {
        "id_review": "ChZDSUhNMG9nS0VJQ0FnSUNJcHRqWVl3EAE",
        "caption": "",
        "relative_date": "2 years ago",
        "retrieval_date": "2021-04-03",
        "rating": 5.0,
        "username": "David Yang",
        "n_review_user": 0,
        "n_photo_user": 0,
        "url_user": "https://www.google.com/maps/contrib/100566879055388942554/reviews?hl=en-US",
        "census_block_group": 360470191003
    },
    {
        "id_review": "ChdDSUhNMG9nS0VJQ0FnSUR3c3E3S3VnRRAB",
        "caption": "",
        "relative_date": "2 years ago",
        "retrieval_date": "2021-04-03",
        "rating": 3.0,
        "username": "Prem Nirmal",
        "n_review_user": 9,
        "n_photo_user": 0,
        "url_user": "https://www.google.com/maps/contrib/104566486614105999906/reviews?hl=en-US",
        "census_block_group": 360470191003
    },
    {
        "id_review": "ChZDSUhNMG9nS0VJQ0FnSUR3MU9HallnEAE",
        "caption": "Banana bread was good, but the hot chocolate was tasteless and poorly made",
        "relative_date": "2 years ago",
        "retrieval_date": "2021-04-03",
        "rating": 1.0,
        "username": "Leslie Vanni",
        "n_review_user": 0,
        "n_photo_user": 0,
        "url_user": "https://www.google.com/maps/contrib/118387982374926552237/reviews?hl=en-US",
        "census_block_group": 360470191003
    },
    {
        "id_review": "ChZDSUhNMG9nS0VJQ0FnSUR3d0p2WUJREAE",
        "caption": "Delicious!",
        "relative_date": "2 years ago",
        "retrieval_date": "2021-04-03",
        "rating": 5.0,
        "username": "Heath McCasland",
        "n_review_user": 0,
        "n_photo_user": 0,
        "url_user": "https://www.google.com/maps/contrib/116994622281177271830/reviews?hl=en-US",
        "census_block_group": 360470191003
    },
    {
        "id_review": "ChdDSUhNMG9nS0VJQ0FnSURBMU9uNWhnRRAB",
        "caption": "at first i was excited about this place but in recent months it has become so average, at best. giving 2 stars for the 2 food items that i enjoy: the farmers muffin and the shakshuka sandwich. oh and the backyard patio is nice.  otherwise, overpriced and overrated all around - a large iced coffee that is bland AF is $5 and their specialty drinks are made sloppily and not mixed properly, not to mention those only come in one size.  the entire staff is cold and bothered all the time, they act like it\u2019s a burden and an annoyance when you simply place your order. i was literally sighed at and get an eye roll. as a business owner just down the street, the quality of the service is so terrible it doesn\u2019t make up for the food given how many other better places there are around. highly disappointing.",
        "relative_date": "2 years ago",
        "retrieval_date": "2021-04-03",
        "rating": 2.0,
        "username": "the wild kind beauty",
        "n_review_user": 4,
        "n_photo_user": 0,
        "url_user": "https://www.google.com/maps/contrib/115264222768931075911/reviews?hl=en-US",
        "census_block_group": 360470191003
    },
    {
        "id_review": "ChZDSUhNMG9nS0VJQ0FnSUNBcUxMcWVBEAE",
        "caption": "Kyle made me a check with a letter explaining his situation, thank you. call me anytime you need me.",
        "relative_date": "2 years ago",
        "retrieval_date": "2021-04-03",
        "rating": 5.0,
        "username": "luis zavala",
        "n_review_user": 4,
        "n_photo_user": 0,
        "url_user": "https://www.google.com/maps/contrib/108127465217857254438/reviews?hl=en-US",
        "census_block_group": 360470191003
    },
    {
        "id_review": "ChZDSUhNMG9nS0VJQ0FnSUNnOF9QNlNBEAE",
        "caption": "Our breakfast were great.  The staff was nice",
        "relative_date": "2 years ago",
        "retrieval_date": "2021-04-03",
        "rating": 5.0,
        "username": "Alexandre V-Dubois",
        "n_review_user": 0,
        "n_photo_user": 0,
        "url_user": "https://www.google.com/maps/contrib/111189413636771399379/reviews?hl=en-US",
        "census_block_group": 360470191003
    },
    {
        "id_review": "ChdDSUhNMG9nS0VJQ0FnSURRMk5fX2dnRRAB",
        "caption": "",
        "relative_date": "2 years ago",
        "retrieval_date": "2021-04-03",
        "rating": 5.0,
        "username": "Shawn Busteed",
        "n_review_user": 0,
        "n_photo_user": 0,
        "url_user": "https://www.google.com/maps/contrib/100139219820950264706/reviews?hl=en-US",
        "census_block_group": 360470191003
    },
    {
        "id_review": "ChZDSUhNMG9nS0VJQ0FnSURnMC1LMkhREAE",
        "caption": "yasss, this place is delicious. The cook is always late!",
        "relative_date": "2 years ago",
        "retrieval_date": "2021-04-03",
        "rating": 5.0,
        "username": "Janice Mandry",
        "n_review_user": 0,
        "n_photo_user": 0,
        "url_user": "https://www.google.com/maps/contrib/109533800222193054534/reviews?hl=en-US",
        "census_block_group": 360470191003
    },
    {
        "id_review": "ChdDSUhNMG9nS0VJQ0FnSUNndDR2aTV3RRAB",
        "caption": "",
        "relative_date": "2 years ago",
        "retrieval_date": "2021-04-03",
        "rating": 4.0,
        "username": "Rahul Pradhan",
        "n_review_user": 0,
        "n_photo_user": 0,
        "url_user": "https://www.google.com/maps/contrib/102358767018124202187/reviews?hl=en-US",
        "census_block_group": 360470191003
    },
    {
        "id_review": "ChdDSUhNMG9nS0VJQ0FnSUNBMnZySnhnRRAB",
        "caption": "Great food and service!",
        "relative_date": "2 years ago",
        "retrieval_date": "2021-04-03",
        "rating": 5.0,
        "username": "Vardon Marshall",
        "n_review_user": 14,
        "n_photo_user": 0,
        "url_user": "https://www.google.com/maps/contrib/114795437176440317844/reviews?hl=en-US",
        "census_block_group": 360470191003
    },
    {
        "id_review": "ChZDSUhNMG9nS0VJQ0FnSURBNTVlV1NBEAE",
        "caption": "",
        "relative_date": "2 years ago",
        "retrieval_date": "2021-04-03",
        "rating": 4.0,
        "username": "Nicole Murray",
        "n_review_user": 0,
        "n_photo_user": 0,
        "url_user": "https://www.google.com/maps/contrib/110534452372281056267/reviews?hl=en-US",
        "census_block_group": 360470191003
    },
    {
        "id_review": "ChZDSUhNMG9nS0VJQ0FnSUNRaDhHdEl3EAE",
        "caption": "Nice selection of overpriced foods and beverages. The service is so painfully slow that even if you're not in a hurry you're going to be annoyed. I try to only visit if I must.",
        "relative_date": "2 years ago",
        "retrieval_date": "2021-04-03",
        "rating": 2.0,
        "username": "Brit Cochran",
        "n_review_user": 4,
        "n_photo_user": 0,
        "url_user": "https://www.google.com/maps/contrib/112448606063273578016/reviews?hl=en-US",
        "census_block_group": 360470191003
    },
    {
        "id_review": "ChdDSUhNMG9nS0VJQ0FnSUN3eXZfUDZnRRAB",
        "caption": "Super tasty, love the eddies ego sammy",
        "relative_date": "2 years ago",
        "retrieval_date": "2021-04-03",
        "rating": 5.0,
        "username": "Chris Van Doren",
        "n_review_user": 0,
        "n_photo_user": 0,
        "url_user": "https://www.google.com/maps/contrib/105395005922272444337/reviews?hl=en-US",
        "census_block_group": 360470191003
    },
    {
        "id_review": "ChdDSUhNMG9nS0VJQ0FnSURRXzQzVmlnRRAB",
        "caption": "",
        "relative_date": "2 years ago",
        "retrieval_date": "2021-04-03",
        "rating": 5.0,
        "username": "Quangkhai Ngole",
        "n_review_user": 0,
        "n_photo_user": 0,
        "url_user": "https://www.google.com/maps/contrib/117405851459063107071/reviews?hl=en-US",
        "census_block_group": 360470191003
    },
    {
        "id_review": "ChdDSUhNMG9nS0VJQ0FnSUNRM0xuc2lBRRAB",
        "caption": "",
        "relative_date": "2 years ago",
        "retrieval_date": "2021-04-03",
        "rating": 5.0,
        "username": "Jennifer McCarthy",
        "n_review_user": 0,
        "n_photo_user": 0,
        "url_user": "https://www.google.com/maps/contrib/102838758110071833574/reviews?hl=en-US",
        "census_block_group": 360470191003
    },
    {
        "id_review": "ChdDSUhNMG9nS0VJQ0FnSUNBMDhmUzV3RRAB",
        "caption": "Staff are \"semi tolerant\" of customers at best. Corn muffin was dry and inedible. Iced latte was good, noticed small writing at the bottom of the posted menu that read additional charge of 50 cents for iced\ud83d\ude44",
        "relative_date": "2 years ago",
        "retrieval_date": "2021-04-03",
        "rating": 2.0,
        "username": "key jay",
        "n_review_user": 0,
        "n_photo_user": 0,
        "url_user": "https://www.google.com/maps/contrib/114264457323904086139/reviews?hl=en-US",
        "census_block_group": 360470191003
    },
    {
        "id_review": "ChdDSUhNMG9nS0VJQ0FnSUNRNHRHNXVnRRAB",
        "caption": "(Translated by Google) Good coffee and a pleasant terrace inside, as opposed to the somewhat impersonal customer service.  (Original) Buen caf\u00e9 y una terraza agradable en su interior, por contra el trato hacia el cliente un tanto impersonal",
        "relative_date": "2 years ago",
        "retrieval_date": "2021-04-03",
        "rating": 4.0,
        "username": "Francisco Campillo",
        "n_review_user": 12,
        "n_photo_user": 0,
        "url_user": "https://www.google.com/maps/contrib/109375731335355333525/reviews?hl=en-US",
        "census_block_group": 360470191003
    },
    {
        "id_review": "ChdDSUhNMG9nS0VJQ0FnSUN3cHZ1bnBRRRAB",
        "caption": "Sandwiches so good! Cheese? Yes pleez! Beer!",
        "relative_date": "2 years ago",
        "retrieval_date": "2021-04-03",
        "rating": 5.0,
        "username": "Benjamin Braudy",
        "n_review_user": 0,
        "n_photo_user": 0,
        "url_user": "https://www.google.com/maps/contrib/110512548288637289959/reviews?hl=en-US",
        "census_block_group": 360470191003
    },
    {
        "id_review": "ChZDSUhNMG9nS0VJQ0FnSUNRc2U2M0pBEAE",
        "caption": "",
        "relative_date": "2 years ago",
        "retrieval_date": "2021-04-03",
        "rating": 5.0,
        "username": "Tricia Terrell",
        "n_review_user": 23,
        "n_photo_user": 0,
        "url_user": "https://www.google.com/maps/contrib/112496811461299128950/reviews?hl=en-US",
        "census_block_group": 360470191003
    },
    {
        "id_review": "ChZDSUhNMG9nS0VJQ0FnSURBNzRySlR3EAE",
        "caption": "",
        "relative_date": "2 years ago",
        "retrieval_date": "2021-04-03",
        "rating": 5.0,
        "username": "Ian Fleming",
        "n_review_user": 0,
        "n_photo_user": 0,
        "url_user": "https://www.google.com/maps/contrib/107386002788283036358/reviews?hl=en-US",
        "census_block_group": 360470191003
    },
    {
        "id_review": "ChZDSUhNMG9nS0VJQ0FnSUNBeUl6NUpREAE",
        "caption": "I've never gone to Peck's, gotten a sandwich and left feeling like I could have put my money to better use. The prepared food here is honestly fantastic and since it's near my laundromat, it's given me a reason to rejoice when I'm in the neighborhood. There's a lovely backyard you can enjoy when it's nice out and they've also got WiFi.",
        "relative_date": "2 years ago",
        "retrieval_date": "2021-04-03",
        "rating": 5.0,
        "username": "Stefan De Clercq",
        "n_review_user": 0,
        "n_photo_user": 0,
        "url_user": "https://www.google.com/maps/contrib/108688046477368311620/reviews?hl=en-US",
        "census_block_group": 360470191003
    },
    {
        "id_review": "ChZDSUhNMG9nS0VJQ0FnSURRbk12RFFREAE",
        "caption": "",
        "relative_date": "3 years ago",
        "retrieval_date": "2021-04-03",
        "rating": 3.0,
        "username": "Amir Khan",
        "n_review_user": 0,
        "n_photo_user": 0,
        "url_user": "https://www.google.com/maps/contrib/114128521063692056178/reviews?hl=en-US",
        "census_block_group": 360470191003
    },
    {
        "id_review": "ChZDSUhNMG9nS0VJQ0FnSUNRbXYtLVFnEAE",
        "caption": "",
        "relative_date": "3 years ago",
        "retrieval_date": "2021-04-03",
        "rating": 5.0,
        "username": "Ice in the house",
        "n_review_user": 6,
        "n_photo_user": 0,
        "url_user": "https://www.google.com/maps/contrib/107457665864902208376/reviews?hl=en-US",
        "census_block_group": 360470191003
    },
    {
        "id_review": "ChdDSUhNMG9nS0VJQ0FnSURnak5Dci1BRRAB",
        "caption": "Peck\u2019s is one of the best coffee shops in the area. Excellent coffee and a good selection of pastries. Everything is freshly baked and prepared. They often have sessional pastries, and special foods for holidays. The baristas are friendly. They sell breakfast sandwiches and prepared food as well. Both are a little pricey, in my opinion, but the quality is worth the price.",
        "relative_date": "3 years ago",
        "retrieval_date": "2021-04-03",
        "rating": 5.0,
        "username": "Vince",
        "n_review_user": 0,
        "n_photo_user": 0,
        "url_user": "https://www.google.com/maps/contrib/115244422015923338312/reviews?hl=en-US",
        "census_block_group": 360470191003
    },
    {
        "id_review": "ChdDSUhNMG9nS0VJQ0FnSUNBLUxyZ3VRRRAB",
        "caption": "Honestly, this is the best coffee on this section of Myrtle near Pratt Institute. They also have a nice selection of market goods along the side including La Colombe and Joe beans.",
        "relative_date": "3 years ago",
        "retrieval_date": "2021-04-03",
        "rating": 4.0,
        "username": "Isabelle Sichler",
        "n_review_user": 2,
        "n_photo_user": 0,
        "url_user": "https://www.google.com/maps/contrib/114583314189385550586/reviews?hl=en-US",
        "census_block_group": 360470191003
    },
    {
        "id_review": "ChdDSUhNMG9nS0VJQ0FnSURBNV92NzNnRRAB",
        "caption": "Great place . Attention to detail .outstanding sandwhich selection . Best Breakfast Sandwich on the block. Theo is doing it Right. Tasty fresh baked snacks to be had ...just had a pistachio and chocolate crossiant that was nothing short of incredible..pecks is a great  place to shop at .good things await you",
        "relative_date": "3 years ago",
        "retrieval_date": "2021-04-03",
        "rating": 5.0,
        "username": "chris caracciolo",
        "n_review_user": 0,
        "n_photo_user": 0,
        "url_user": "https://www.google.com/maps/contrib/114832815149675760712/reviews?hl=en-US",
        "census_block_group": 360470191003
    },
    {
        "id_review": "ChdDSUhNMG9nS0VJQ0FnSUNnZ05HV3B3RRAB",
        "caption": "",
        "relative_date": "3 years ago",
        "retrieval_date": "2021-04-03",
        "rating": 4.0,
        "username": "Charles Nelson",
        "n_review_user": 0,
        "n_photo_user": 0,
        "url_user": "https://www.google.com/maps/contrib/106567913195726541076/reviews?hl=en-US",
        "census_block_group": 360470191003
    },
    {
        "id_review": "ChdDSUhNMG9nS0VJQ0FnSURBaTd6Zy13RRAB",
        "caption": "Just amazing!!",
        "relative_date": "3 years ago",
        "retrieval_date": "2021-04-03",
        "rating": 5.0,
        "username": "Yvan Larry",
        "n_review_user": 2,
        "n_photo_user": 0,
        "url_user": "https://www.google.com/maps/contrib/102255082106073797615/reviews?hl=en-US",
        "census_block_group": 360470191003
    },
    {
        "id_review": "ChZDSUhNMG9nS0VJQ0FnSURnMVBUMUpREAE",
        "caption": "Great food/drink. Friendly service.",
        "relative_date": "3 years ago",
        "retrieval_date": "2021-04-03",
        "rating": 5.0,
        "username": "Arnold Sanchez",
        "n_review_user": 0,
        "n_photo_user": 0,
        "url_user": "https://www.google.com/maps/contrib/113676030232607684242/reviews?hl=en-US",
        "census_block_group": 360470191003
    },
    {
        "id_review": "ChdDSUhNMG9nS0VJQ0FnSURnX3FhMWhnRRAB",
        "caption": "",
        "relative_date": "3 years ago",
        "retrieval_date": "2021-04-03",
        "rating": 4.0,
        "username": "floris dekker",
        "n_review_user": 0,
        "n_photo_user": 0,
        "url_user": "https://www.google.com/maps/contrib/110213821336268247700/reviews?hl=en-US",
        "census_block_group": 360470191003
    },
    {
        "id_review": "ChZDSUhNMG9nS0VJQ0FnSUN3OGM3RFJBEAE",
        "caption": "I can't quite figure out if Peck's is a coffee shop or a little food market. There's virtually no seating inside, but they do have a spacious backyard that is perfect for the warmer months. The staff is neither friendly nor rude, but they do their job well. If you're into La Colombe coffee this place won't disappoint.",
        "relative_date": "3 years ago",
        "retrieval_date": "2021-04-03",
        "rating": 4.0,
        "username": "Stephen Elliot",
        "n_review_user": 0,
        "n_photo_user": 0,
        "url_user": "https://www.google.com/maps/contrib/108727815673924857440/reviews?hl=en-US",
        "census_block_group": 360470191003
    },
    {
        "id_review": "ChdDSUhNMG9nS0VJQ0FnSUNRb2VMLXBBRRAB",
        "caption": "",
        "relative_date": "3 years ago",
        "retrieval_date": "2021-04-03",
        "rating": 5.0,
        "username": "Diana Valdiserri",
        "n_review_user": 0,
        "n_photo_user": 0,
        "url_user": "https://www.google.com/maps/contrib/114860280239874396535/reviews?hl=en-US",
        "census_block_group": 360470191003
    },
    {
        "id_review": "ChZDSUhNMG9nS0VJQ0FnSUNRd1Azb0NnEAE",
        "caption": "I've had their sandwiches and fresh made goods before and it's very good, but I ordered their pre packaged eggplant parm and asked it to be heated up today, it was barely luke warm and it tasted like it was sour or off. I wouldn't recommend anything pre packaged, stick to anything that's fresh off the menu.",
        "relative_date": "3 years ago",
        "retrieval_date": "2021-04-03",
        "rating": 2.0,
        "username": "Nigel Sequeira",
        "n_review_user": 0,
        "n_photo_user": 0,
        "url_user": "https://www.google.com/maps/contrib/104119715268619893252/reviews?hl=en-US",
        "census_block_group": 360470191003
    },
    {
        "id_review": "ChZDSUhNMG9nS0VJQ0FnSUN3a3JlM2J3EAE",
        "caption": "Good coffee, breakfast sandwiches,  and charcuterie",
        "relative_date": "3 years ago",
        "retrieval_date": "2021-04-03",
        "rating": 5.0,
        "username": "Jordan Brock",
        "n_review_user": 0,
        "n_photo_user": 0,
        "url_user": "https://www.google.com/maps/contrib/109453881833505560768/reviews?hl=en-US",
        "census_block_group": 360470191003
    },
    {
        "id_review": "ChdDSUhNMG9nS0VJQ0FnSUNBcjVEb2dnRRAB",
        "caption": "A cozy, family-owned deli and bakery. The hot sandwich menu always has delicious options. But the highlight of this place are the pastries. Highly recommended for coffee and pastries. There's a back yard area which is great in the summers.",
        "relative_date": "3 years ago",
        "retrieval_date": "2021-04-03",
        "rating": 5.0,
        "username": "Althea Labre",
        "n_review_user": 0,
        "n_photo_user": 0,
        "url_user": "https://www.google.com/maps/contrib/109889109965757395821/reviews?hl=en-US",
        "census_block_group": 360470191003
    },
    {
        "id_review": "ChdDSUhNMG9nS0VJQ0FnSURRZ2RiTzd3RRAB",
        "caption": "",
        "relative_date": "3 years ago",
        "retrieval_date": "2021-04-03",
        "rating": 5.0,
        "username": "Simon-Emanuel Balint",
        "n_review_user": 1,
        "n_photo_user": 0,
        "url_user": "https://www.google.com/maps/contrib/102021099839594330891/reviews?hl=en-US",
        "census_block_group": 360470191003
    },
    {
        "id_review": "ChZDSUhNMG9nS0VJQ0FnSURRX3FMN2JREAE",
        "caption": "",
        "relative_date": "3 years ago",
        "retrieval_date": "2021-04-03",
        "rating": 5.0,
        "username": "Ben Roth",
        "n_review_user": 0,
        "n_photo_user": 0,
        "url_user": "https://www.google.com/maps/contrib/107794597341745940569/reviews?hl=en-US",
        "census_block_group": 360470191003
    },
    {
        "id_review": "ChZDSUhNMG9nS0VJQ0FnSURRdkppb0lnEAE",
        "caption": "",
        "relative_date": "3 years ago",
        "retrieval_date": "2021-04-03",
        "rating": 5.0,
        "username": "Michael Havis",
        "n_review_user": 0,
        "n_photo_user": 0,
        "url_user": "https://www.google.com/maps/contrib/105631281902711527202/reviews?hl=en-US",
        "census_block_group": 360470191003
    },
    {
        "id_review": "ChdDSUhNMG9nS0VJQ0FnSUNBaWNfNy13RRAB",
        "caption": "Delicious sandwiches and great (albeit expensive) craft beer selection. Lovely patio too!",
        "relative_date": "3 years ago",
        "retrieval_date": "2021-04-03",
        "rating": 5.0,
        "username": "Marcy Buccellato",
        "n_review_user": 0,
        "n_photo_user": 0,
        "url_user": "https://www.google.com/maps/contrib/115095380393914655691/reviews?hl=en-US",
        "census_block_group": 360470191003
    },
    {
        "id_review": "ChdDSUhNMG9nS0VJQ0FnSURBLVlmVjZ3RRAB",
        "caption": "",
        "relative_date": "3 years ago",
        "retrieval_date": "2021-04-03",
        "rating": 5.0,
        "username": "H.B. Nelson, Jr.",
        "n_review_user": 0,
        "n_photo_user": 0,
        "url_user": "https://www.google.com/maps/contrib/108057454925305204192/reviews?hl=en-US",
        "census_block_group": 360470191003
    },
    {
        "id_review": "ChZDSUhNMG9nS0VJQ0FnSUNBZ05qN0F3EAE",
        "caption": "",
        "relative_date": "3 years ago",
        "retrieval_date": "2021-04-03",
        "rating": 5.0,
        "username": "Behnaz Amery",
        "n_review_user": 0,
        "n_photo_user": 0,
        "url_user": "https://www.google.com/maps/contrib/103053419196591031216/reviews?hl=en-US",
        "census_block_group": 360470191003
    },
    {
        "id_review": "ChZDSUhNMG9nS0VJQ0FnSUNRa2NIS0h3EAE",
        "caption": "Lovely outside garden patio. Tasty sandwiches. Quick and easy, although not necessarily cheap.",
        "relative_date": "3 years ago",
        "retrieval_date": "2021-04-03",
        "rating": 5.0,
        "username": "Tim Valshtein",
        "n_review_user": 0,
        "n_photo_user": 0,
        "url_user": "https://www.google.com/maps/contrib/102026522152646666219/reviews?hl=en-US",
        "census_block_group": 360470191003
    },
    {
        "id_review": "ChdDSUhNMG9nS0VJQ0FnSUN3akpId3p3RRAB",
        "caption": "",
        "relative_date": "3 years ago",
        "retrieval_date": "2021-04-03",
        "rating": 5.0,
        "username": "Deborah Wheatley",
        "n_review_user": 7,
        "n_photo_user": 0,
        "url_user": "https://www.google.com/maps/contrib/104084193395957967170/reviews?hl=en-US",
        "census_block_group": 360470191003
    },
    {
        "id_review": "ChdDSUhNMG9nS0VJQ0FnSUNnbi1ESHZnRRAB",
        "caption": "",
        "relative_date": "3 years ago",
        "retrieval_date": "2021-04-03",
        "rating": 5.0,
        "username": "Tamara Hicks",
        "n_review_user": 5,
        "n_photo_user": 0,
        "url_user": "https://www.google.com/maps/contrib/100758872952908150866/reviews?hl=en-US",
        "census_block_group": 360470191003
    },
    {
        "id_review": "ChZDSUhNMG9nS0VJQ0FnSUNBX01feUt3EAE",
        "caption": "Try the Jewish Pope, and a k'nish.",
        "relative_date": "3 years ago",
        "retrieval_date": "2021-04-03",
        "rating": 5.0,
        "username": "Joel Silverstein",
        "n_review_user": 2,
        "n_photo_user": 0,
        "url_user": "https://www.google.com/maps/contrib/113890554442486476809/reviews?hl=en-US",
        "census_block_group": 360470191003
    },
    {
        "id_review": "ChdDSUhNMG9nS0VJQ0FnSURnXzlMZmx3RRAB",
        "caption": "Poor customer service. Bad food quality. If cook isn't there there isn't food. Cashier limits herself to cash and make coffee, very unhelpfull. Always carry attitude. When cook is there, he is willing to cook and help. Last time I went veggie sandwich was bad. Chicken without taste. Won't ever come back.",
        "relative_date": "3 years ago",
        "retrieval_date": "2021-04-03",
        "rating": 1.0,
        "username": "Silvia Luque",
        "n_review_user": 3,
        "n_photo_user": 0,
        "url_user": "https://www.google.com/maps/contrib/112266598268095362370/reviews?hl=en-US",
        "census_block_group": 360470191003
    },
    {
        "id_review": "ChZDSUhNMG9nS0VJQ0FnSUNnaEthdGZnEAE",
        "caption": "I bought a rosteried chiken here and it was horrible. Costumer service horrible, very unsupportive. they don't cut the chicken and it is $26. this chiken has not flavor at all, not sauce, and people that work here doesn't help we eat the chiken without sauce and they gave me 2 very small plates for a whole chiken.",
        "relative_date": "3 years ago",
        "retrieval_date": "2021-04-03",
        "rating": 1.0,
        "username": "Aldi Palucio",
        "n_review_user": 11,
        "n_photo_user": 0,
        "url_user": "https://www.google.com/maps/contrib/116250047891231803963/reviews?hl=en-US",
        "census_block_group": 360470191003
    },
    {
        "id_review": "ChdDSUhNMG9nS0VJQ0FnSUNROF8zTTJRRRAB",
        "caption": "Great food. Slow slow service",
        "relative_date": "3 years ago",
        "retrieval_date": "2021-04-03",
        "rating": 4.0,
        "username": "Morgan Strecker",
        "n_review_user": 6,
        "n_photo_user": 0,
        "url_user": "https://www.google.com/maps/contrib/104219983414881811188/reviews?hl=en-US",
        "census_block_group": 360470191003
    },
    {
        "id_review": "ChdDSUhNMG9nS0VJQ0FnSUNBcjZ2MDZBRRAB",
        "caption": "",
        "relative_date": "3 years ago",
        "retrieval_date": "2021-04-03",
        "rating": 3.0,
        "username": "Jonathan Wing",
        "n_review_user": 2,
        "n_photo_user": 0,
        "url_user": "https://www.google.com/maps/contrib/115412319197793266581/reviews?hl=en-US",
        "census_block_group": 360470191003
    },
    {
        "id_review": "ChZDSUhNMG9nS0VJQ0FnSUNRdHYzalBBEAE",
        "caption": "I go to Peck's at least three times a week during the school year. Theo and Kyle run a great shop. Make sure to check out the backyard!",
        "relative_date": "3 years ago",
        "retrieval_date": "2021-04-03",
        "rating": 5.0,
        "username": "Damien Duchamp",
        "n_review_user": 0,
        "n_photo_user": 0,
        "url_user": "https://www.google.com/maps/contrib/117211861934152840756/reviews?hl=en-US",
        "census_block_group": 360470191003
    },
    {
        "id_review": "ChZDSUhNMG9nS0VJQ0FnSURnaUpiaGJnEAE",
        "caption": "",
        "relative_date": "3 years ago",
        "retrieval_date": "2021-04-03",
        "rating": 5.0,
        "username": "Alex Kalaf",
        "n_review_user": 0,
        "n_photo_user": 0,
        "url_user": "https://www.google.com/maps/contrib/105888846125202641146/reviews?hl=en-US",
        "census_block_group": 360470191003
    },
    {
        "id_review": "ChdDSUhNMG9nS0VJQ0FnSURBeHAyRGl3RRAB",
        "caption": "Great sandwiches, snacks, pantry items and beer.",
        "relative_date": "3 years ago",
        "retrieval_date": "2021-04-03",
        "rating": 5.0,
        "username": "Brian Buccellato",
        "n_review_user": 0,
        "n_photo_user": 0,
        "url_user": "https://www.google.com/maps/contrib/109473236154111312146/reviews?hl=en-US",
        "census_block_group": 360470191003
    },
    {
        "id_review": "ChZDSUhNMG9nS0VJQ0FnSUNRc3BhSWZBEAE",
        "caption": "Awesome spot for baked goods, craft sandwiches, and provisions! Peck's has an awesome selection of Evil Twin and other brews, and the breakfast sandwiches are some of the best around. If they have the halva brownie, it's a must-try!",
        "relative_date": "3 years ago",
        "retrieval_date": "2021-04-03",
        "rating": 5.0,
        "username": "Mariel Henkoff",
        "n_review_user": 0,
        "n_photo_user": 0,
        "url_user": "https://www.google.com/maps/contrib/101930931999793382745/reviews?hl=en-US",
        "census_block_group": 360470191003
    },
    {
        "id_review": "ChZDSUhNMG9nS0VJQ0FnSUN3bTkyS1dBEAE",
        "caption": "Great espresso, cold brew on tap, yum yum bakery treats",
        "relative_date": "3 years ago",
        "retrieval_date": "2021-04-03",
        "rating": 5.0,
        "username": "stacey a. keith",
        "n_review_user": 0,
        "n_photo_user": 0,
        "url_user": "https://www.google.com/maps/contrib/105809092695711645647/reviews?hl=en-US",
        "census_block_group": 360470191003
    },
    {
        "id_review": "ChZDSUhNMG9nS0VJQ0FnSUNRMTRiVFdnEAE",
        "caption": "",
        "relative_date": "3 years ago",
        "retrieval_date": "2021-04-03",
        "rating": 5.0,
        "username": "ricardo cruz",
        "n_review_user": 0,
        "n_photo_user": 0,
        "url_user": "https://www.google.com/maps/contrib/103047220142452298161/reviews?hl=en-US",
        "census_block_group": 360470191003
    },
    {
        "id_review": "ChZDSUhNMG9nS0VJQ0FnSURnaGVfVkxREAE",
        "caption": "",
        "relative_date": "3 years ago",
        "retrieval_date": "2021-04-03",
        "rating": 4.0,
        "username": "Joana Pacheco",
        "n_review_user": 11,
        "n_photo_user": 0,
        "url_user": "https://www.google.com/maps/contrib/117337643455205351886/reviews?hl=en-US",
        "census_block_group": 360470191003
    },
    {
        "id_review": "ChdDSUhNMG9nS0VJQ0FnSUNndl8tSzZ3RRAB",
        "caption": "Great sandwiches, delicious baked goods and well curated assortment of grocery items.",
        "relative_date": "3 years ago",
        "retrieval_date": "2021-04-03",
        "rating": 5.0,
        "username": "Justin Birchard",
        "n_review_user": 0,
        "n_photo_user": 0,
        "url_user": "https://www.google.com/maps/contrib/102229483362748690352/reviews?hl=en-US",
        "census_block_group": 360470191003
    },
    {
        "id_review": "ChdDSUhNMG9nS0VJQ0FnSUNBei1mWXBBRRAB",
        "caption": "",
        "relative_date": "3 years ago",
        "retrieval_date": "2021-04-03",
        "rating": 2.0,
        "username": "Christina Socias",
        "n_review_user": 0,
        "n_photo_user": 0,
        "url_user": "https://www.google.com/maps/contrib/105213440771692480025/reviews?hl=en-US",
        "census_block_group": 360470191003
    },
    {
        "id_review": "ChdDSUhNMG9nS0VJQ0FnSURBMXNXWjFnRRAB",
        "caption": "",
        "relative_date": "3 years ago",
        "retrieval_date": "2021-04-03",
        "rating": 5.0,
        "username": "Aur\u00e9lia Courtot",
        "n_review_user": 0,
        "n_photo_user": 0,
        "url_user": "https://www.google.com/maps/contrib/110242009234915837671/reviews?hl=en-US",
        "census_block_group": 360470191003
    },
    {
        "id_review": "ChZDSUhNMG9nS0VJQ0FnSUNRNjdpWUVREAE",
        "caption": "",
        "relative_date": "3 years ago",
        "retrieval_date": "2021-04-03",
        "rating": 4.0,
        "username": "Scott Wagner",
        "n_review_user": 0,
        "n_photo_user": 0,
        "url_user": "https://www.google.com/maps/contrib/102684016573611315901/reviews?hl=en-US",
        "census_block_group": 360470191003
    },
    {
        "id_review": "ChZDSUhNMG9nS0VJQ0FnSUNncU1pT0lnEAE",
        "caption": "THOSE BREAKFAST SANDWICHES!!! Great coffee also. And looks like a promising spot to get some interesting ingredients for the kitchen.",
        "relative_date": "3 years ago",
        "retrieval_date": "2021-04-03",
        "rating": 5.0,
        "username": "Kris Hooper",
        "n_review_user": 0,
        "n_photo_user": 0,
        "url_user": "https://www.google.com/maps/contrib/109438747458801648489/reviews?hl=en-US",
        "census_block_group": 360470191003
    },
    {
        "id_review": "ChZDSUhNMG9nS0VJQ0FnSUN3b3BDYlVBEAE",
        "caption": "Peck's, when you're asked to make coffee drinks TO STAY, don't use PAPER CUPS! When you're asked many, many times to make it to stay, and you still grab a paper cup, times and again, you lose any credibility as a coffee shop. Not to mention the poor job you do with your espresso based drinks, and how insanely overpriced your shop is overall.",
        "relative_date": "4 years ago",
        "retrieval_date": "2021-04-03",
        "rating": 2.0,
        "username": "Sasha Malchik",
        "n_review_user": 0,
        "n_photo_user": 0,
        "url_user": "https://www.google.com/maps/contrib/105930416159570983936/reviews?hl=en-US",
        "census_block_group": 360470191003
    },
    {
        "id_review": "ChZDSUhNMG9nS0VJQ0FnSURBdXBlcWFREAE",
        "caption": "This place has coffee which is needed or else we get crabby. Cookies too pretty nice, not cheap tho.",
        "relative_date": "4 years ago",
        "retrieval_date": "2021-04-03",
        "rating": 4.0,
        "username": "Dan Splains",
        "n_review_user": 0,
        "n_photo_user": 0,
        "url_user": "https://www.google.com/maps/contrib/113277172245437803003/reviews?hl=en-US",
        "census_block_group": 360470191003
    },
    {
        "id_review": "ChdDSUhNMG9nS0VJQ0FnSUNRbzRfOTRRRRAB",
        "caption": "",
        "relative_date": "4 years ago",
        "retrieval_date": "2021-04-03",
        "rating": 5.0,
        "username": "Anne Hathaway",
        "n_review_user": 0,
        "n_photo_user": 0,
        "url_user": "https://www.google.com/maps/contrib/105521936257964179962/reviews?hl=en-US",
        "census_block_group": 360470191003
    },
    {
        "id_review": "ChdDSUhNMG9nS0VJQ0FnSUNnaXFDZnR3RRAB",
        "caption": "Great baked goods, fresh salads and veggies to go, and great coffee.",
        "relative_date": "4 years ago",
        "retrieval_date": "2021-04-03",
        "rating": 5.0,
        "username": "matthew epler",
        "n_review_user": 8,
        "n_photo_user": 0,
        "url_user": "https://www.google.com/maps/contrib/118319050543607777197/reviews?hl=en-US",
        "census_block_group": 360470191003
    },
    {
        "id_review": "ChdDSUhNMG9nS0VJQ0FnSUN3cElEZjRBRRAB",
        "caption": "$8 matzo ball soup wasn't even that good and had raw veggies in it. Not worth more than $2  Roasted chickens are solid",
        "relative_date": "4 years ago",
        "retrieval_date": "2021-04-03",
        "rating": 2.0,
        "username": "Josh Thomases",
        "n_review_user": 3,
        "n_photo_user": 0,
        "url_user": "https://www.google.com/maps/contrib/108260181076481425665/reviews?hl=en-US",
        "census_block_group": 360470191003
    },
    {
        "id_review": "ChdDSUhNMG9nS0VJQ0FnSUNBX2ZYVnN3RRAB",
        "caption": "Delicious. Theo Peck is great.",
        "relative_date": "4 years ago",
        "retrieval_date": "2021-04-03",
        "rating": 5.0,
        "username": "Jeffery Gleaves",
        "n_review_user": 0,
        "n_photo_user": 0,
        "url_user": "https://www.google.com/maps/contrib/104427967608061044832/reviews?hl=en-US",
        "census_block_group": 360470191003
    },
    {
        "id_review": "ChZDSUhNMG9nS0VJQ0FnSUNBdWY3SVh3EAE",
        "caption": "",
        "relative_date": "4 years ago",
        "retrieval_date": "2021-04-03",
        "rating": 5.0,
        "username": "Dillon Hamilton",
        "n_review_user": 0,
        "n_photo_user": 0,
        "url_user": "https://www.google.com/maps/contrib/100550865337160311820/reviews?hl=en-US",
        "census_block_group": 360470191003
    },
    {
        "id_review": "ChdDSUhNMG9nS0VJQ0FnSUN3cUlMZ25RRRAB",
        "caption": "Great food, great coffee, and great staff. This place is a must-try if you're in the area.",
        "relative_date": "4 years ago",
        "retrieval_date": "2021-04-03",
        "rating": 5.0,
        "username": "Kevin McCormick",
        "n_review_user": 0,
        "n_photo_user": 0,
        "url_user": "https://www.google.com/maps/contrib/110107522096806392625/reviews?hl=en-US",
        "census_block_group": 360470191003
    },
    {
        "id_review": "ChZDSUhNMG9nS0VJQ0FnSUNnMjZ5MUdnEAE",
        "caption": "",
        "relative_date": "4 years ago",
        "retrieval_date": "2021-04-03",
        "rating": 4.0,
        "username": "Philip Kalmes",
        "n_review_user": 1,
        "n_photo_user": 0,
        "url_user": "https://www.google.com/maps/contrib/102067381387996425445/reviews?hl=en-US",
        "census_block_group": 360470191003
    },
    {
        "id_review": "ChdDSUhNMG9nS0VJQ0FnSUNBcS1ycHFBRRAB",
        "caption": "",
        "relative_date": "4 years ago",
        "retrieval_date": "2021-04-03",
        "rating": 5.0,
        "username": "Michael Ossege",
        "n_review_user": 0,
        "n_photo_user": 0,
        "url_user": "https://www.google.com/maps/contrib/115018697088412829575/reviews?hl=en-US",
        "census_block_group": 360470191003
    },
    {
        "id_review": "ChdDSUhNMG9nS0VJQ0FnSUNnOFp6Qnh3RRAB",
        "caption": "just got one of their roast chickens.  OMG  delicious.  cooked perfectly!!!",
        "relative_date": "4 years ago",
        "retrieval_date": "2021-04-03",
        "rating": 5.0,
        "username": "Denise Andres",
        "n_review_user": 2,
        "n_photo_user": 0,
        "url_user": "https://www.google.com/maps/contrib/103456233278871808112/reviews?hl=en-US",
        "census_block_group": 360470191003
    },
    {
        "id_review": "ChZDSUhNMG9nS0VJQ0FnSUNnbS1tZmVnEAE",
        "caption": "Great menu.",
        "relative_date": "4 years ago",
        "retrieval_date": "2021-04-03",
        "rating": 5.0,
        "username": "Harry Hawk",
        "n_review_user": 0,
        "n_photo_user": 0,
        "url_user": "https://www.google.com/maps/contrib/113879793828770728039/reviews?hl=en-US",
        "census_block_group": 360470191003
    },
    {
        "id_review": "ChZDSUhNMG9nS0VJQ0FnSUNnaTl5TVJBEAE",
        "caption": "",
        "relative_date": "4 years ago",
        "retrieval_date": "2021-04-03",
        "rating": 5.0,
        "username": "Ryan Balch",
        "n_review_user": 0,
        "n_photo_user": 0,
        "url_user": "https://www.google.com/maps/contrib/105725400048507516033/reviews?hl=en-US",
        "census_block_group": 360470191003
    },
    {
        "id_review": "ChZDSUhNMG9nS0VJQ0FnSURRM05IbEt3EAE",
        "caption": "",
        "relative_date": "4 years ago",
        "retrieval_date": "2021-04-03",
        "rating": 5.0,
        "username": "Melchior Scholler",
        "n_review_user": 11,
        "n_photo_user": 0,
        "url_user": "https://www.google.com/maps/contrib/111207976274562370204/reviews?hl=en-US",
        "census_block_group": 360470191003
    },
    {
        "id_review": "ChdDSUhNMG9nS0VJQ0FnSUNReFlqSjFnRRAB",
        "caption": "",
        "relative_date": "4 years ago",
        "retrieval_date": "2021-04-03",
        "rating": 5.0,
        "username": "\u00e9douard",
        "n_review_user": 3,
        "n_photo_user": 0,
        "url_user": "https://www.google.com/maps/contrib/109058532832252110925/reviews?hl=en-US",
        "census_block_group": 360470191003
    },
    {
        "id_review": "ChdDSUhNMG9nS0VJQ0FnSURnaUxhenpnRRAB",
        "caption": "The folks at Peck's have more than your typical coffee/tea/craft beer/fancy provisions. Great spot for charcuterie, awesome prepared foods and friendly staff.",
        "relative_date": "4 years ago",
        "retrieval_date": "2021-04-03",
        "rating": 5.0,
        "username": "Chris Maddern",
        "n_review_user": 0,
        "n_photo_user": 0,
        "url_user": "https://www.google.com/maps/contrib/105632254738821762305/reviews?hl=en-US",
        "census_block_group": 360470191003
    },
    {
        "id_review": "ChdDSUhNMG9nS0VJQ0FnSURRbHIzX3hBRRAB",
        "caption": "My favorite neighborhood coffee shop. We get the breakfast sandwich - without bread (gluten-free family) - all the time!  Great coffee, cheese , meat and deli counter. GREAT staff and service. Friendly, quick, and they remember our names and favorite drinks.",
        "relative_date": "4 years ago",
        "retrieval_date": "2021-04-03",
        "rating": 5.0,
        "username": "Alexandra Jamieson",
        "n_review_user": 0,
        "n_photo_user": 0,
        "url_user": "https://www.google.com/maps/contrib/105231133065033076341/reviews?hl=en-US",
        "census_block_group": 360470191003
    },
    {
        "id_review": "ChdDSUhNMG9nS0VJQ0FnSUNRc3FfTW9RRRAB",
        "caption": "Yummy Latte!",
        "relative_date": "4 years ago",
        "retrieval_date": "2021-04-03",
        "rating": 4.0,
        "username": "Sarah Southgate",
        "n_review_user": 0,
        "n_photo_user": 0,
        "url_user": "https://www.google.com/maps/contrib/111209193273299757561/reviews?hl=en-US",
        "census_block_group": 360470191003
    },
    {
        "id_review": "ChdDSUhNMG9nS0VJQ0FnSURBaVlmb2hnRRAB",
        "caption": "Great place",
        "relative_date": "4 years ago",
        "retrieval_date": "2021-04-03",
        "rating": 5.0,
        "username": "Robert Nelson",
        "n_review_user": 0,
        "n_photo_user": 0,
        "url_user": "https://www.google.com/maps/contrib/116681914340940527123/reviews?hl=en-US",
        "census_block_group": 360470191003
    },
    {
        "id_review": "ChZDSUhNMG9nS0VJQ0FnSUNBOWFuTlRREAE",
        "caption": "Awesome pastry.. kitchen has gone down hill recently.",
        "relative_date": "4 years ago",
        "retrieval_date": "2021-04-03",
        "rating": 5.0,
        "username": "Jason Holloway",
        "n_review_user": 0,
        "n_photo_user": 0,
        "url_user": "https://www.google.com/maps/contrib/106086011433878971090/reviews?hl=en-US",
        "census_block_group": 360470191003
    },
    {
        "id_review": "ChdDSUhNMG9nS0VJQ0FnSUNnaGNxMXBnRRAB",
        "caption": "",
        "relative_date": "4 years ago",
        "retrieval_date": "2021-04-03",
        "rating": 4.0,
        "username": "Alec Cohen",
        "n_review_user": 0,
        "n_photo_user": 0,
        "url_user": "https://www.google.com/maps/contrib/107077688491065650456/reviews?hl=en-US",
        "census_block_group": 360470191003
    },
    {
        "id_review": "ChdDSUhNMG9nS0VJQ0FnSUNRdGZyamxnRRAB",
        "caption": "Im not a coffee connoisseur at all but I just got a regular coffee with almond milk  and it was amazing! Plus the baristas are all attractive. Always a plus",
        "relative_date": "5 years ago",
        "retrieval_date": "2021-04-03",
        "rating": 5.0,
        "username": "Julia",
        "n_review_user": 0,
        "n_photo_user": 0,
        "url_user": "https://www.google.com/maps/contrib/116189255319821899124/reviews?hl=en-US",
        "census_block_group": 360470191003
    },
    {
        "id_review": "ChZDSUhNMG9nS0VJQ0FnSUNRclBhOUl3EAE",
        "caption": "The best chocolate chip cookies, macaroons, and other savory treats. Also on the weekend the chocolate cinnamon babka roll is absolutely the best ever!",
        "relative_date": "5 years ago",
        "retrieval_date": "2021-04-03",
        "rating": 5.0,
        "username": "Paul Baudier",
        "n_review_user": 0,
        "n_photo_user": 0,
        "url_user": "https://www.google.com/maps/contrib/117989069838807695500/reviews?hl=en-US",
        "census_block_group": 360470191003
    },
    {
        "id_review": "ChZDSUhNMG9nS0VJQ0FnSURBdl9EQldREAE",
        "caption": "",
        "relative_date": "5 years ago",
        "retrieval_date": "2021-04-03",
        "rating": 5.0,
        "username": "Lydia White",
        "n_review_user": 2,
        "n_photo_user": 0,
        "url_user": "https://www.google.com/maps/contrib/104601554079185842347/reviews?hl=en-US",
        "census_block_group": 360470191003
    },
    {
        "id_review": "ChdDSUhNMG9nS0VJQ0FnSUNndnJ6ZG53RRAB",
        "caption": "",
        "relative_date": "5 years ago",
        "retrieval_date": "2021-04-03",
        "rating": 4.0,
        "username": "Michael Romanos",
        "n_review_user": 0,
        "n_photo_user": 0,
        "url_user": "https://www.google.com/maps/contrib/109848798458627714202/reviews?hl=en-US",
        "census_block_group": 360470191003
    },
    {
        "id_review": "ChZDSUhNMG9nS0VJQ0FnSURBOHFhT2FREAE",
        "caption": "",
        "relative_date": "5 years ago",
        "retrieval_date": "2021-04-03",
        "rating": 5.0,
        "username": "Anna Fusco",
        "n_review_user": 3,
        "n_photo_user": 0,
        "url_user": "https://www.google.com/maps/contrib/117693240486826862461/reviews?hl=en-US",
        "census_block_group": 360470191003
    },
    {
        "id_review": "ChZDSUhNMG9nS0VJQ0FnSURna0tqX0hBEAE",
        "caption": "Superb establishment; delicious eats and warm staff. A real 'local'.",
        "relative_date": "5 years ago",
        "retrieval_date": "2021-04-03",
        "rating": 5.0,
        "username": "Jerry Pura",
        "n_review_user": 1,
        "n_photo_user": 0,
        "url_user": "https://www.google.com/maps/contrib/111723100849849289907/reviews?hl=en-US",
        "census_block_group": 360470191003
    }
]