[
      {
            "business_status":"OPERATIONAL",
            "geometry":{
                  "location":{
                        "lat":34.0834302,
                        "lng":-118.2234686
                  },
                  "viewport":{
                        "northeast":{
                              "lat":34.0847549803,
                              "lng":-118.2219749697
                        },
                        "southwest":{
                              "lat":34.0820570197,
                              "lng":-118.2246729303
                        }
                  }
            },
            "icon":"https:\/\/maps.gstatic.com\/mapfiles\/place_api\/icons\/v1\/png_71\/restaurant-71.png",
            "name":"IHOP",
            "opening_hours":{
                  "open_now":false
            },
            "photos":[
                  {
                        "height":2976,
                        "html_attributions":[
                              "<a href=\"https:\/\/maps.google.com\/maps\/contrib\/102403121870611399080\">Yasir Mansouri<\/a>"
                        ],
                        "photo_reference":"ATtYBwKtBfxjzfVCgDcJ08cC1JHnaG5GhSo-y_X6prHRoRx0RJ91ofcQ-AUzEJGwBvdkecS3xeP4b5o66eybekinjDRpXM5C7xrLav5vRoNYviTfhwC6z6YW4XsU6JzhVgurrBA5dJ60qm8UjHx0sWSijxuHrQ_nSvDfpGS4m79qtyY-odvu",
                        "width":3968
                  }
            ],
            "place_id":"ChIJNZnFA5LGwoARFLcZIl_M8p4",
            "plus_code":{
                  "compound_code":"3QMG+9J Los Angeles, CA, USA",
                  "global_code":"85633QMG+9J"
            },
            "price_level":1.0,
            "rating":4.2,
            "reference":"ChIJNZnFA5LGwoARFLcZIl_M8p4",
            "scope":"GOOGLE",
            "types":[
                  "restaurant",
                  "food",
                  "point_of_interest",
                  "establishment"
            ],
            "user_ratings_total":1797.0,
            "vicinity":"2227 North Figueroa Street, Los Angeles",
            "CBG":60371853202,
            "Radius":347.2457409459
      },
      {
            "business_status":"OPERATIONAL",
            "geometry":{
                  "location":{
                        "lat":34.086665,
                        "lng":-118.223824
                  },
                  "viewport":{
                        "northeast":{
                              "lat":34.0880468803,
                              "lng":-118.2225140697
                        },
                        "southwest":{
                              "lat":34.0853489197,
                              "lng":-118.2252120303
                        }
                  }
            },
            "icon":"https:\/\/maps.gstatic.com\/mapfiles\/place_api\/icons\/v1\/png_71\/restaurant-71.png",
            "name":"Lupita's Restaurant",
            "opening_hours":{
                  "open_now":false
            },
            "photos":[
                  {
                        "height":3024,
                        "html_attributions":[
                              "<a href=\"https:\/\/maps.google.com\/maps\/contrib\/105402508862380922650\">Damian Lavalle<\/a>"
                        ],
                        "photo_reference":"ATtYBwLGCfen1G5gz0yWGi0fFNG_ykRPK3hoEXHckGUY_D4WAIEG_U6wcqjGYrCSKojWi-WCiWi8Cj5X8HCFNBB_VdrUzj6z95h5-113s0jIty7SIZmdT-UkV7BVKnxlpcKTsW9UfFqiZVmWJrmKH4gR5AgyxikgC4iFf6ORgCQaqsYavSM7",
                        "width":4032
                  }
            ],
            "place_id":"ChIJiVdK25PGwoARuZRfxnJasT0",
            "plus_code":{
                  "compound_code":"3QPG+MF Los Angeles, CA, USA",
                  "global_code":"85633QPG+MF"
            },
            "price_level":1.0,
            "rating":4.5,
            "reference":"ChIJiVdK25PGwoARuZRfxnJasT0",
            "scope":"GOOGLE",
            "types":[
                  "restaurant",
                  "food",
                  "point_of_interest",
                  "establishment"
            ],
            "user_ratings_total":198.0,
            "vicinity":"2634 Idell Street, Los Angeles",
            "CBG":60371853202,
            "Radius":347.2457409459
      },
      {
            "business_status":"OPERATIONAL",
            "geometry":{
                  "location":{
                        "lat":34.084496,
                        "lng":-118.223167
                  },
                  "viewport":{
                        "northeast":{
                              "lat":34.0858241803,
                              "lng":-118.2218466697
                        },
                        "southwest":{
                              "lat":34.0831262197,
                              "lng":-118.2245446303
                        }
                  }
            },
            "icon":"https:\/\/maps.gstatic.com\/mapfiles\/place_api\/icons\/v1\/png_71\/restaurant-71.png",
            "name":"La Morena Hot Dogs",
            "opening_hours":{
                  "open_now":false
            },
            "photos":[
                  {
                        "height":1080,
                        "html_attributions":[
                              "<a href=\"https:\/\/maps.google.com\/maps\/contrib\/111258554466535275411\">La Morena Hot Dogs<\/a>"
                        ],
                        "photo_reference":"ATtYBwLZyxRL3-FCBkC3nfUW9f0B21vssz6FLb8BHhC_7CWKZRVgYyK7jIz_64N4kmTVLz4uoVB1cvs0yE36OMfyKgDlkuvMjpyS8nJn1wbitL3XBRubGKyC_JhZ9dtJcvvLrEaN5cogmU3lQzE1_hMZCmZCx_jsRGLu6xnfnMC-yPM2SOhe",
                        "width":1080
                  }
            ],
            "place_id":"ChIJW4Q2R7PHwoAREMwgxt2ARJE",
            "plus_code":{
                  "compound_code":"3QMG+QP Los Angeles, CA, USA",
                  "global_code":"85633QMG+QP"
            },
            "price_level":null,
            "rating":5.0,
            "reference":"ChIJW4Q2R7PHwoAREMwgxt2ARJE",
            "scope":"GOOGLE",
            "types":[
                  "meal_takeaway",
                  "restaurant",
                  "food",
                  "point_of_interest",
                  "establishment"
            ],
            "user_ratings_total":4.0,
            "vicinity":"HURON ST, West Avenue 26, Los Angeles",
            "CBG":60371853202,
            "Radius":347.2457409459
      },
      {
            "business_status":"OPERATIONAL",
            "geometry":{
                  "location":{
                        "lat":34.0848981,
                        "lng":-118.2222349
                  },
                  "viewport":{
                        "northeast":{
                              "lat":34.0860971803,
                              "lng":-118.2209347197
                        },
                        "southwest":{
                              "lat":34.0833992197,
                              "lng":-118.2236326803
                        }
                  }
            },
            "icon":"https:\/\/maps.gstatic.com\/mapfiles\/place_api\/icons\/v1\/png_71\/restaurant-71.png",
            "name":"Wingstop",
            "opening_hours":{
                  "open_now":false
            },
            "photos":[
                  {
                        "height":2160,
                        "html_attributions":[
                              "<a href=\"https:\/\/maps.google.com\/maps\/contrib\/107767824248426910279\">Clinton Wager<\/a>"
                        ],
                        "photo_reference":"ATtYBwJVVNlYJYRigafBcAa1avZvCms9T8J4934uoyOLQWE59kzsB2_JJlnrHez7YomsDMtw9CRfE85ao74V0v3OlOc5SMI4hu_Wg0z-lq38OP9eEBrfY-fJx19l9Ce5omdv8r09ULr0BypVRD3OxOTsYJaD13EZ2udNWGbnCYXqI8nTC67x",
                        "width":3840
                  }
            ],
            "place_id":"ChIJZbNr6tLHwoARLGe2skz93cI",
            "plus_code":{
                  "compound_code":"3QMH+X4 Los Angeles, CA, USA",
                  "global_code":"85633QMH+X4"
            },
            "price_level":2.0,
            "rating":3.4,
            "reference":"ChIJZbNr6tLHwoARLGe2skz93cI",
            "scope":"GOOGLE",
            "types":[
                  "restaurant",
                  "food",
                  "point_of_interest",
                  "establishment"
            ],
            "user_ratings_total":51.0,
            "vicinity":"2619 North Figueroa Street Ste C, Los Angeles",
            "CBG":60371853202,
            "Radius":347.2457409459
      },
      {
            "business_status":"OPERATIONAL",
            "geometry":{
                  "location":{
                        "lat":34.0848981,
                        "lng":-118.2222349
                  },
                  "viewport":{
                        "northeast":{
                              "lat":34.0860971803,
                              "lng":-118.2209347197
                        },
                        "southwest":{
                              "lat":34.0833992197,
                              "lng":-118.2236326803
                        }
                  }
            },
            "icon":"https:\/\/maps.gstatic.com\/mapfiles\/place_api\/icons\/v1\/png_71\/restaurant-71.png",
            "name":"Panda Express",
            "opening_hours":{
                  "open_now":false
            },
            "photos":[
                  {
                        "height":3120,
                        "html_attributions":[
                              "<a href=\"https:\/\/maps.google.com\/maps\/contrib\/103978482692456072496\">Julio Martinez Col\u00ecn<\/a>"
                        ],
                        "photo_reference":"ATtYBwKf_T4udcNK7tit5U2S4r4u9OEjQ8Yj2-1pc8pKHuWAi83Nyusjrnndil1vMCpSZ-MEbcg5ezbjuAYQ-pablutiPJbRHmXGba8l1tFPpWzyddsuzkgzODYZLfgBxf-TNsarQ4CjraRDrzRaYgrf2h5etKzx-uzayenroK39ABK5U3yr",
                        "width":4160
                  }
            ],
            "place_id":"ChIJof-3KbbHwoARk_waN0bHuP4",
            "plus_code":{
                  "compound_code":"3QMH+X4 Los Angeles, CA, USA",
                  "global_code":"85633QMH+X4"
            },
            "price_level":1.0,
            "rating":3.0,
            "reference":"ChIJof-3KbbHwoARk_waN0bHuP4",
            "scope":"GOOGLE",
            "types":[
                  "restaurant",
                  "food",
                  "point_of_interest",
                  "establishment"
            ],
            "user_ratings_total":24.0,
            "vicinity":"2619 North Figueroa Street, Los Angeles",
            "CBG":60371853202,
            "Radius":347.2457409459
      },
      {
            "business_status":"OPERATIONAL",
            "geometry":{
                  "location":{
                        "lat":34.0841116,
                        "lng":-118.2224573
                  },
                  "viewport":{
                        "northeast":{
                              "lat":34.0855105803,
                              "lng":-118.2210570697
                        },
                        "southwest":{
                              "lat":34.0828126197,
                              "lng":-118.2237550303
                        }
                  }
            },
            "icon":"https:\/\/maps.gstatic.com\/mapfiles\/place_api\/icons\/v1\/png_71\/restaurant-71.png",
            "name":"Alfredo's Fruit Cart and Special Events",
            "opening_hours":{
                  "open_now":false
            },
            "photos":null,
            "place_id":"ChIJmyjNc2fHwoARD0XHMl-Hb4g",
            "plus_code":{
                  "compound_code":"3QMH+J2 Glassell Park, Los Angeles, CA, USA",
                  "global_code":"85633QMH+J2"
            },
            "price_level":null,
            "rating":null,
            "reference":"ChIJmyjNc2fHwoARD0XHMl-Hb4g",
            "scope":"GOOGLE",
            "types":[
                  "restaurant",
                  "food",
                  "point_of_interest",
                  "establishment"
            ],
            "user_ratings_total":null,
            "vicinity":"Glassell Park",
            "CBG":60371853202,
            "Radius":347.2457409459
      },
      {
            "business_status":"OPERATIONAL",
            "geometry":{
                  "location":{
                        "lat":34.0850602,
                        "lng":-118.2211531
                  },
                  "viewport":{
                        "northeast":{
                              "lat":34.0863549303,
                              "lng":-118.2197303697
                        },
                        "southwest":{
                              "lat":34.0836569697,
                              "lng":-118.2224283303
                        }
                  }
            },
            "icon":"https:\/\/maps.gstatic.com\/mapfiles\/place_api\/icons\/v1\/png_71\/restaurant-71.png",
            "name":"Aide's caf\u00e9 and juices",
            "opening_hours":{
                  "open_now":false
            },
            "photos":[
                  {
                        "height":2048,
                        "html_attributions":[
                              "<a href=\"https:\/\/maps.google.com\/maps\/contrib\/113541999266134487177\">Aide&#39;s caf\u00e9 and juices<\/a>"
                        ],
                        "photo_reference":"ATtYBwKxFkLoEXiehYPyUYuy6XhUhta-Mj_E1zhimGJzE4FtdcABFbZqZelASVcdYaB5A-lGGM91rOfQWI7kqvU66oSM3-vjGHJgcJSgyUibTmYg6-kJKxH1Y9rMkjnid2u-Zy0Mu0LSOnm--XvijdphGyrCCTytNJNLb8bz8w_JWRCkbA3h",
                        "width":1536
                  }
            ],
            "place_id":"ChIJ2zcIyZHGwoARb09vpKuQ_q4",
            "plus_code":{
                  "compound_code":"3QPH+2G Los Angeles, CA, USA",
                  "global_code":"85633QPH+2G"
            },
            "price_level":null,
            "rating":4.9,
            "reference":"ChIJ2zcIyZHGwoARb09vpKuQ_q4",
            "scope":"GOOGLE",
            "types":[
                  "restaurant",
                  "cafe",
                  "food",
                  "point_of_interest",
                  "store",
                  "establishment"
            ],
            "user_ratings_total":22.0,
            "vicinity":"2805 North Figueroa Street, Los Angeles",
            "CBG":60371853202,
            "Radius":347.2457409459
      },
      {
            "business_status":"OPERATIONAL",
            "geometry":{
                  "location":{
                        "lat":34.0841509,
                        "lng":-118.2216185
                  },
                  "viewport":{
                        "northeast":{
                              "lat":34.0855882803,
                              "lng":-118.2203656197
                        },
                        "southwest":{
                              "lat":34.0828903197,
                              "lng":-118.2230635803
                        }
                  }
            },
            "icon":"https:\/\/maps.gstatic.com\/mapfiles\/place_api\/icons\/v1\/png_71\/restaurant-71.png",
            "name":"Rosita Mexican Restaurant",
            "opening_hours":{
                  "open_now":false
            },
            "photos":[
                  {
                        "height":4640,
                        "html_attributions":[
                              "<a href=\"https:\/\/maps.google.com\/maps\/contrib\/102708203875895785441\">Sergio Ramirez<\/a>"
                        ],
                        "photo_reference":"ATtYBwL5wYVPkh04s6wSIju49CGrWF0vy3VNm8gJQg8Re9NYd1EcvUzh92a4fg5mZmezOe4HLOBQOIsUreQ3bg2sZeAQPMPNJS4OygV0Fe8unIW2df56Ic_lEUDY58d4fwAUxMsngK21b4TNZYYE3P3V2nufMhsscnaNRn4nIK5_3w3Aa3ud",
                        "width":2320
                  }
            ],
            "place_id":"ChIJD7Jf25HGwoARE4XhRFKo6rg",
            "plus_code":{
                  "compound_code":"3QMH+M9 Los Angeles, CA, USA",
                  "global_code":"85633QMH+M9"
            },
            "price_level":null,
            "rating":3.8,
            "reference":"ChIJD7Jf25HGwoARE4XhRFKo6rg",
            "scope":"GOOGLE",
            "types":[
                  "restaurant",
                  "food",
                  "point_of_interest",
                  "establishment"
            ],
            "user_ratings_total":30.0,
            "vicinity":"2622 North Figueroa Street, Los Angeles",
            "CBG":60371853202,
            "Radius":347.2457409459
      },
      {
            "business_status":"OPERATIONAL",
            "geometry":{
                  "location":{
                        "lat":34.0847364,
                        "lng":-118.2208657
                  },
                  "viewport":{
                        "northeast":{
                              "lat":34.0860918303,
                              "lng":-118.2196886697
                        },
                        "southwest":{
                              "lat":34.0833938697,
                              "lng":-118.2223866303
                        }
                  }
            },
            "icon":"https:\/\/maps.gstatic.com\/mapfiles\/place_api\/icons\/v1\/png_71\/restaurant-71.png",
            "name":"Restaurant Arroyo Hall",
            "opening_hours":{
                  "open_now":false
            },
            "photos":null,
            "place_id":"ChIJcxIXaizHwoAR6r0Sc9hcIvQ",
            "plus_code":{
                  "compound_code":"3QMH+VM Los Angeles, CA, USA",
                  "global_code":"85633QMH+VM"
            },
            "price_level":null,
            "rating":5.0,
            "reference":"ChIJcxIXaizHwoAR6r0Sc9hcIvQ",
            "scope":"GOOGLE",
            "types":[
                  "restaurant",
                  "food",
                  "point_of_interest",
                  "establishment"
            ],
            "user_ratings_total":1.0,
            "vicinity":"2806 North Figueroa Street, Los Angeles",
            "CBG":60371853202,
            "Radius":347.2457409459
      },
      {
            "business_status":"OPERATIONAL",
            "geometry":{
                  "location":{
                        "lat":34.0831146,
                        "lng":-118.2228148
                  },
                  "viewport":{
                        "northeast":{
                              "lat":34.0844378803,
                              "lng":-118.2215964197
                        },
                        "southwest":{
                              "lat":34.0817399197,
                              "lng":-118.2242943803
                        }
                  }
            },
            "icon":"https:\/\/maps.gstatic.com\/mapfiles\/place_api\/icons\/v1\/png_71\/restaurant-71.png",
            "name":"McDonald's",
            "opening_hours":{
                  "open_now":true
            },
            "photos":[
                  {
                        "height":3024,
                        "html_attributions":[
                              "<a href=\"https:\/\/maps.google.com\/maps\/contrib\/111196179223292793481\">Hama Ayu<\/a>"
                        ],
                        "photo_reference":"ATtYBwJvVHewJ_pXyffYLazvQvRHwVdcdjajwJTxRix8hfQJll1KpH1A6R_GdofQEkorDTOwiBu8a5CB6nCrfz-2IzCH5Hx1PbEhVLNsPgaJcbBH4DFdknybd5rqRapq47DzTo7CHINOJT_m7JgFFBbbnJvWih-R2s_mEdrAZbHtqLeIUJSu",
                        "width":4032
                  }
            ],
            "place_id":"ChIJt-bhAI7GwoARwyyWiT5WIJI",
            "plus_code":{
                  "compound_code":"3QMG+6V Los Angeles, CA, USA",
                  "global_code":"85633QMG+6V"
            },
            "price_level":1.0,
            "rating":3.8,
            "reference":"ChIJt-bhAI7GwoARwyyWiT5WIJI",
            "scope":"GOOGLE",
            "types":[
                  "cafe",
                  "restaurant",
                  "food",
                  "point_of_interest",
                  "store",
                  "establishment"
            ],
            "user_ratings_total":1280.0,
            "vicinity":"2224 North Figueroa Street, Los Angeles",
            "CBG":60371853202,
            "Radius":347.2457409459
      },
      {
            "business_status":"OPERATIONAL",
            "geometry":{
                  "location":{
                        "lat":34.0830313,
                        "lng":-118.2240134
                  },
                  "viewport":{
                        "northeast":{
                              "lat":34.0843170303,
                              "lng":-118.2227144697
                        },
                        "southwest":{
                              "lat":34.0816190697,
                              "lng":-118.2254124303
                        }
                  }
            },
            "icon":"https:\/\/maps.gstatic.com\/mapfiles\/place_api\/icons\/v1\/png_71\/restaurant-71.png",
            "name":"Las Quesadillas",
            "opening_hours":null,
            "photos":[
                  {
                        "height":3024,
                        "html_attributions":[
                              "<a href=\"https:\/\/maps.google.com\/maps\/contrib\/107954776896258648533\">Tere Santiago<\/a>"
                        ],
                        "photo_reference":"ATtYBwKW22TQO72Mk9MhDgqXlBckKP9Yg7l6qBbkisMChyD3SUzRE0mh2T4gDDoAIFCaGUP_ciFKo7spwpitv-eL0yfNoHIanT4dFc9lXxPB36sJUI_v1djU5pKSMpHgjN3sEOXeyK4-AgA7FLNDCqnEUCh-NzjmbjwisxotwFp2Eh_9ah9C",
                        "width":4032
                  }
            ],
            "place_id":"ChIJRcgBBezHwoARmx6gltg1ojM",
            "plus_code":{
                  "compound_code":"3QMG+69 Los Angeles, CA, USA",
                  "global_code":"85633QMG+69"
            },
            "price_level":null,
            "rating":3.3,
            "reference":"ChIJRcgBBezHwoARmx6gltg1ojM",
            "scope":"GOOGLE",
            "types":[
                  "restaurant",
                  "food",
                  "point_of_interest",
                  "establishment"
            ],
            "user_ratings_total":3.0,
            "vicinity":"5446013059, Los Angeles",
            "CBG":60371853202,
            "Radius":347.2457409459
      }
]